{"__type__":"sp.SkeletonData","_name":"putongniu","_skeletonJson":{"skeleton":{"hash":"KusBQbI3Ia+Z7tS+V0vZHGsygYw","spine":"3.7.94","width":260.42,"height":60.13,"images":"./images/","audio":"E:/77/新0/游戏/牛牛/无牛"},"bones":[{"name":"root"},{"name":"wenzi","parent":"root","x":1.91,"y":3.63},{"name":"di","parent":"root","x":0.13,"y":2.87},{"name":"wenzi2","parent":"root","x":1.91,"y":3.63},{"name":"yun","parent":"root","x":95.75,"y":-6.47},{"name":"yun2","parent":"root","x":-92.01,"y":-6.8,"scaleX":-1},{"name":"hulu","parent":"root","x":98.18,"y":10.74},{"name":"hulu1","parent":"root","x":-95.12,"y":12.78}],"slots":[{"name":"di","bone":"di","attachment":"di"},{"name":"yun","bone":"yun","attachment":"yun"},{"name":"yun2","bone":"yun2","attachment":"yun"},{"name":"niu1","bone":"wenzi","attachment":"niu1"},{"name":"niu7","bone":"wenzi2","attachment":"niu1","blend":"additive"},{"name":"niu2","bone":"wenzi","attachment":"niu2"},{"name":"niu8","bone":"wenzi2","attachment":"niu2","blend":"additive"},{"name":"niu3","bone":"wenzi","attachment":"niu3"},{"name":"niu9","bone":"wenzi2","attachment":"niu3","blend":"additive"},{"name":"niu4","bone":"wenzi","attachment":"niu4"},{"name":"niu10","bone":"wenzi2","attachment":"niu4","blend":"additive"},{"name":"niu5","bone":"wenzi","attachment":"niu5"},{"name":"niu11","bone":"wenzi2","attachment":"niu5","blend":"additive"},{"name":"niu6","bone":"wenzi","attachment":"niu6"},{"name":"niu12","bone":"wenzi2","attachment":"niu6","blend":"additive"},{"name":"hulu","bone":"hulu","attachment":"hulu"},{"name":"hulu1","bone":"hulu1","attachment":"hulu1"}],"skins":{"default":{"di":{"di":{"x":-0.37,"y":-2.37,"width":235,"height":56}},"hulu":{"hulu":{"x":-0.51,"y":-3.1,"width":33,"height":46}},"hulu1":{"hulu1":{"x":0.67,"y":-3.16,"width":33,"height":46}},"yun":{"yun":{"x":-3.17,"y":0.85,"width":79,"height":32}},"yun2":{"yun":{"x":-3.17,"y":0.85,"width":79,"height":32}}},"niu1":{"niu1":{"niu1":{"x":0.5,"y":0.5,"width":127,"height":37}},"niu7":{"niu1":{"x":0.5,"y":0.5,"width":127,"height":37}}},"niu2":{"niu2":{"niu2":{"x":0.5,"y":0.5,"width":127,"height":37}},"niu8":{"niu2":{"x":0.5,"y":0.5,"width":127,"height":37}}},"niu3":{"niu3":{"niu3":{"y":0.5,"width":127,"height":37}},"niu9":{"niu3":{"y":0.5,"width":127,"height":37}}},"niu4":{"niu10":{"niu4":{"y":0.5,"width":127,"height":37}},"niu4":{"niu4":{"y":0.5,"width":127,"height":37}}},"niu5":{"niu11":{"niu5":{"y":0.5,"width":127,"height":37}},"niu5":{"niu5":{"y":0.5,"width":127,"height":37}}},"niu6":{"niu12":{"niu6":{"x":0.5,"y":0.5,"width":127,"height":37}},"niu6":{"niu6":{"x":0.5,"y":0.5,"width":127,"height":37}}}},"animations":{"animation":{"slots":{"hulu":{"color":[{"time":0,"color":"ffffff00","curve":"stepped"},{"time":0.3,"color":"ffffff00"},{"time":0.6667,"color":"ffffffff"}]},"hulu1":{"color":[{"time":0,"color":"ffffff00","curve":"stepped"},{"time":0.3,"color":"ffffff00"},{"time":0.6667,"color":"ffffffff"}]},"niu1":{"color":[{"time":0,"color":"ffffff00","curve":"stepped"},{"time":0.2,"color":"ffffff00"},{"time":0.5,"color":"ffffffff"}]},"niu2":{"color":[{"time":0,"color":"ffffff00","curve":"stepped"},{"time":0.2,"color":"ffffff00"},{"time":0.5,"color":"ffffffff"}]},"niu3":{"color":[{"time":0,"color":"ffffff00","curve":"stepped"},{"time":0.2,"color":"ffffff00"},{"time":0.5,"color":"ffffffff"}]},"niu4":{"color":[{"time":0,"color":"ffffff00","curve":"stepped"},{"time":0.2,"color":"ffffff00"},{"time":0.5,"color":"ffffffff"}]},"niu5":{"color":[{"time":0,"color":"ffffff00","curve":"stepped"},{"time":0.2,"color":"ffffff00"},{"time":0.5,"color":"ffffffff"}]},"niu6":{"color":[{"time":0,"color":"ffffff00","curve":"stepped"},{"time":0.2,"color":"ffffff00"},{"time":0.5,"color":"ffffffff"}]},"niu7":{"color":[{"time":0,"color":"ffffffff","curve":"stepped"},{"time":0.5,"color":"ffffffff"},{"time":0.7667,"color":"ffffff00"}],"attachment":[{"time":0,"name":null},{"time":0.5,"name":"niu1"}]},"niu8":{"color":[{"time":0,"color":"ffffffff","curve":"stepped"},{"time":0.5,"color":"ffffffff"},{"time":0.7667,"color":"ffffff00"}],"attachment":[{"time":0,"name":null},{"time":0.5,"name":"niu2"}]},"niu9":{"color":[{"time":0,"color":"ffffffff","curve":"stepped"},{"time":0.5,"color":"ffffffff"},{"time":0.7667,"color":"ffffff00"}],"attachment":[{"time":0,"name":null},{"time":0.5,"name":"niu3"}]},"niu10":{"color":[{"time":0,"color":"ffffffff","curve":"stepped"},{"time":0.5,"color":"ffffffff"},{"time":0.7667,"color":"ffffff00"}],"attachment":[{"time":0,"name":null},{"time":0.5,"name":"niu4"}]},"niu11":{"color":[{"time":0,"color":"ffffffff","curve":"stepped"},{"time":0.5,"color":"ffffffff"},{"time":0.7667,"color":"ffffff00"}],"attachment":[{"time":0,"name":null},{"time":0.5,"name":"niu5"}]},"niu12":{"color":[{"time":0,"color":"ffffffff","curve":"stepped"},{"time":0.5,"color":"ffffffff"},{"time":0.7667,"color":"ffffff00"}],"attachment":[{"time":0,"name":null},{"time":0.5,"name":"niu6"}]}},"bones":{"di":{"scale":[{"time":0,"x":0,"y":1},{"time":0.2,"x":1,"y":1}]},"wenzi":{"scale":[{"time":0,"x":1.5,"y":1.5,"curve":"stepped"},{"time":0.2,"x":1.5,"y":1.5},{"time":0.5,"x":1,"y":1}]},"wenzi2":{"scale":[{"time":0,"x":1,"y":1,"curve":"stepped"},{"time":0.5,"x":1,"y":1},{"time":0.7667,"x":1.5,"y":1.5}]},"yun":{"translate":[{"time":0,"x":-16.99,"y":0,"curve":"stepped"},{"time":0.2,"x":-16.99,"y":0},{"time":0.5,"x":0,"y":0}],"scale":[{"time":0,"x":0,"y":0,"curve":"stepped"},{"time":0.2,"x":0,"y":0},{"time":0.5,"x":1,"y":1}]},"yun2":{"translate":[{"time":0,"x":5.36,"y":0,"curve":"stepped"},{"time":0.2,"x":5.36,"y":0},{"time":0.5,"x":0,"y":0}],"scale":[{"time":0,"x":0,"y":0,"curve":"stepped"},{"time":0.2,"x":0,"y":0},{"time":0.5,"x":1,"y":1}]},"hulu":{"rotate":[{"time":0,"angle":10,"curve":"stepped"},{"time":0.3,"angle":10},{"time":0.6667,"angle":0}],"translate":[{"time":0,"x":7.69,"y":0,"curve":"stepped"},{"time":0.3,"x":7.69,"y":0},{"time":0.6667,"x":0,"y":0}]},"hulu1":{"rotate":[{"time":0,"angle":-10,"curve":"stepped"},{"time":0.3,"angle":-10},{"time":0.6667,"angle":0}],"translate":[{"time":0,"x":-5.26,"y":0,"curve":"stepped"},{"time":0.3,"x":-5.26,"y":0},{"time":0.6667,"x":0,"y":0}]}}}}},"_atlasText":"\nputongniu.png\nsize: 256,256\nformat: RGBA8888\nfilter: Linear,Linear\nrepeat: none\ndi\n  rotate: false\n  xy: 2, 197\n  size: 235, 56\n  orig: 235, 56\n  offset: 0, 0\n  index: -1\nhulu\n  rotate: false\n  xy: 131, 20\n  size: 33, 46\n  orig: 33, 46\n  offset: 0, 0\n  index: -1\nhulu1\n  rotate: false\n  xy: 204, 149\n  size: 33, 46\n  orig: 33, 46\n  offset: 0, 0\n  index: -1\nniu1\n  rotate: false\n  xy: 2, 158\n  size: 127, 37\n  orig: 127, 37\n  offset: 0, 0\n  index: -1\nniu2\n  rotate: false\n  xy: 2, 119\n  size: 127, 37\n  orig: 127, 37\n  offset: 0, 0\n  index: -1\nniu3\n  rotate: false\n  xy: 2, 80\n  size: 127, 37\n  orig: 127, 37\n  offset: 0, 0\n  index: -1\nniu4\n  rotate: false\n  xy: 2, 41\n  size: 127, 37\n  orig: 127, 37\n  offset: 0, 0\n  index: -1\nniu5\n  rotate: true\n  xy: 131, 68\n  size: 127, 37\n  orig: 127, 37\n  offset: 0, 0\n  index: -1\nniu6\n  rotate: false\n  xy: 2, 2\n  size: 127, 37\n  orig: 127, 37\n  offset: 0, 0\n  index: -1\nyun\n  rotate: true\n  xy: 170, 116\n  size: 79, 32\n  orig: 79, 32\n  offset: 0, 0\n  index: -1\n","textures":[{"__uuid__":"05EqpZV59K3rrSmB7o2oCU"}],"textureNames":["putongniu.png"]}