[[{"__type__":"cc.Prefab","_name":"night_come","data":{"__id__":1}},{"__type__":"cc.Node","_name":"night_come","_children":[{"__id__":2},{"__id__":3}],"_prefab":{"__type__":"cc.PrefabInfo","root":{"__id__":1},"asset":{"__uuid__":"4aeZxsYZ9HYITqHsg3M2Gy"},"fileId":"fc48zSAuhNeail5rz0gEiy"},"_contentSize":{"__type__":"cc.Size","width":1559,"height":205},"_trs":{"__type__":"TypedArray","ctor":"Float64Array","array":[0,0,0,0,0,0,1,1,1,1]}},{"__type__":"cc.Node","_name":"img_di_black","_parent":{"__id__":1},"_components":[{"__type__":"cc.Sprite","node":{"__id__":2},"_materials":[{"__uuid__":"ecpdLyjvZBwrvm+cedCcQy"}],"_spriteFrame":{"__uuid__":"deVoEreoNJqb8bQkCNwvoY"},"_sizeMode":0}],"_prefab":{"__type__":"cc.PrefabInfo","root":{"__id__":1},"asset":{"__uuid__":"4aeZxsYZ9HYITqHsg3M2Gy"},"fileId":"dbNpG3gYdMiJjzpcW0prXd"},"_contentSize":{"__type__":"cc.Size","width":1600,"height":196},"_trs":{"__type__":"TypedArray","ctor":"Float64Array","array":[0,-35,0,0,0,0,1,1,1,1]}},{"__type__":"cc.Node","_name":"img_tianhei","_parent":{"__id__":1},"_components":[{"__type__":"cc.Sprite","node":{"__id__":3},"_materials":[{"__uuid__":"ecpdLyjvZBwrvm+cedCcQy"}],"_spriteFrame":{"__uuid__":"5eEQJmI6VLsp/SrEb+xaEX"}}],"_prefab":{"__type__":"cc.PrefabInfo","root":{"__id__":1},"asset":{"__uuid__":"4aeZxsYZ9HYITqHsg3M2Gy"},"fileId":"9afSWC2RNPjobQHkEn2BWl"},"_contentSize":{"__type__":"cc.Size","width":1559,"height":205},"_trs":{"__type__":"TypedArray","ctor":"Float64Array","array":[0,0,0,0,0,0,1,1,1,1]}}],{"__type__":"cc.SpriteFrame","content":{"name":"img_tianhei","texture":"33lNlH30dOFYb3Q+8MWUug","rect":[0,0,1559,205],"offset":[0,0],"originalSize":[1559,205],"capInsets":[0,0,0,0]}},{"__type__":"cc.SpriteFrame","content":{"name":"img_di_black","texture":"1fd604ce8","rect":[807,518,60,196],"offset":[0,0],"originalSize":[60,196],"rotated":1,"capInsets":[0,0,0,0]}}]