[{"__type__":"cc.SpriteFrame","content":{"name":"img_ltjl_yel","texture":"1994e2620","rect":[285,79,60,184],"offset":[0,0],"originalSize":[60,184],"rotated":1,"capInsets":[0,0,0,0]}},{"__type__":"cc.SpriteFrame","content":{"name":"text_wan_blue","texture":"1994e2620","rect":[453,3,62,23],"offset":[0,0.5],"originalSize":[64,24],"capInsets":[0,0,0,0]}},{"__type__":"cc.SpriteFrame","content":{"name":"img_lrstouxiang","texture":"1994e2620","rect":[798,251,130,129],"offset":[0,-0.5],"originalSize":[130,130],"capInsets":[0,0,0,0]}},{"__type__":"cc.SpriteFrame","content":{"name":"btn_lrs_ksyx","texture":"194ab3360","rect":[398,504,261,80],"offset":[-0.5,0],"originalSize":[262,80],"rotated":1,"capInsets":[0,0,0,0]}},{"__type__":"cc.SpriteFrame","content":{"name":"img_yueliang","texture":"1994e2620","rect":[671,211,121,119],"offset":[0.5,2.5],"originalSize":[124,126],"capInsets":[0,0,0,0]}},{"__type__":"cc.SpriteFrame","content":{"name":"bk_menu","texture":"4e3Uz+qqtAA5YsxFgPcC0F","rect":[0,0,166,351],"offset":[-1,0.5],"originalSize":[168,352],"capInsets":[20,18.5,50,18.5]}},{"__type__":"cc.SpriteFrame","content":{"name":"bg_mianban","texture":"1fd604ce8","rect":[3,3,441,598],"offset":[0.5,-3],"originalSize":[442,610],"capInsets":[0,0,0,0]}},{"__type__":"cc.SpriteFrame","content":{"name":"img_lieren_ff","texture":"194ab3360","rect":[484,453,168,238],"offset":[0,0],"originalSize":[170,238],"rotated":1,"capInsets":[0,0,0,0]}},{"__type__":"cc.SpriteFrame","content":{"name":"line_lrs","texture":"1994e2620","rect":[3,3,304,19],"offset":[0,0.5],"originalSize":[304,20],"capInsets":[0,0,0,0]}},{"__type__":"cc.SpriteFrame","content":{"name":"img_lrstouxiang2","texture":"1994e2620","rect":[561,211,104,104],"offset":[0,0],"originalSize":[130,130],"capInsets":[0,0,0,0]}},{"__type__":"cc.SpriteFrame","content":{"name":"btn_gz","texture":"a9f5ehMTJJ5ox/hiQEM6OP","rect":[5,2,118,37],"offset":[2,1.5],"originalSize":[124,44],"capInsets":[0,0,0,0]}},{"__type__":"cc.SpriteFrame","content":{"name":"default_btn_disabled","texture":"71VhFCTINJM6/Ky3oX9nBT","rect":[0,0,40,40],"offset":[0,0],"originalSize":[40,40],"capInsets":[12,12,12,12]}},{"__type__":"cc.SpriteFrame","content":{"name":"img_kjy_gray","texture":"1994e2620","rect":[475,79,60,184],"offset":[0,0],"originalSize":[60,184],"rotated":1,"capInsets":[0,0,0,0]}},{"__type__":"cc.SpriteFrame","content":{"name":"img_tg03","texture":"03bekLIOxBK6ZSG5WBCe6i","rect":[479,30,124,24],"offset":[0,0],"originalSize":[124,24],"rotated":1,"capInsets":[15,12,15,12]}},{"__type__":"cc.SpriteFrame","content":{"name":"img_langren_ff","texture":"194ab3360","rect":[181,774,169,238],"offset":[-0.5,0],"originalSize":[170,238],"capInsets":[0,0,0,0]}},{"__type__":"cc.SpriteFrame","content":{"name":"img_mianban_new","texture":"194ab3360","rect":[3,3,726,444],"offset":[0,0],"originalSize":[726,444],"capInsets":[0,0,0,0]}},{"__type__":"cc.SpriteFrame","content":{"name":"img_kjy_yel","texture":"1994e2620","rect":[665,79,60,184],"offset":[0,0],"originalSize":[60,184],"rotated":1,"capInsets":[0,0,0,0]}},{"__type__":"cc.SpriteFrame","content":{"name":"img_time_dibu","texture":"1994e2620","rect":[3,418,602,115],"offset":[0,0],"originalSize":[602,115],"capInsets":[0,0,0,0]}},{"__type__":"cc.SpriteFrame","content":{"name":"img_lrs_zz_baitian","texture":"1994e2620","rect":[351,43,30,643],"offset":[0,-38.5],"originalSize":[30,720],"rotated":1,"capInsets":[0,0,0,0]}},{"__type__":"cc.SpriteFrame","content":{"name":"icon_jiaoliu","texture":"1994e2620","rect":[471,211,84,84],"offset":[0,0],"originalSize":[84,84],"capInsets":[0,0,0,0]}},{"__type__":"cc.SpriteFrame","content":{"name":"e001","texture":"1895ac276","rect":[60,909,50,50],"offset":[-2,-1],"originalSize":[56,56],"capInsets":[0,0,0,0]}},{"__type__":"cc.SpriteFrame","content":{"name":"btn_menu","texture":"a6++PODe1JtJPiY/PWNlYT","rect":[0,0,56,77],"offset":[0,0.5],"originalSize":[56,78],"capInsets":[0,0,0,0]}},{"__type__":"cc.SpriteFrame","content":{"name":"img_bq_gray","texture":"1994e2620","rect":[3,135,60,184],"offset":[0,0],"originalSize":[60,184],"rotated":1,"capInsets":[0,0,0,0]}},{"__type__":"cc.SpriteFrame","content":{"name":"img_lrs_zz_wanshang","texture":"1994e2620","rect":[63,65,60,66],"offset":[0,0],"originalSize":[60,66],"rotated":1,"capInsets":[0,0,0,0]}},{"__type__":"cc.SpriteFrame","content":{"name":"btn_tc","texture":"603iBx2rVBeYXJk2W0kK6z","rect":[1,0,122,44],"offset":[0,0],"originalSize":[124,44],"capInsets":[0,0,0,0]}},{"__type__":"cc.SpriteFrame","content":{"name":"line","texture":"91k7vR92lJiJBX20MaPzHR","rect":[0,0,127,9],"offset":[-0.5,0.5],"originalSize":[128,10],"capInsets":[0,0,0,0]}},{"__type__":"cc.SpriteFrame","content":{"name":"bg_lrs","texture":"2dyxYS9YVGFbv7c3lckTPY","rect":[0,0,1559,720],"offset":[0,0],"originalSize":[1559,720],"capInsets":[0,0,0,0]}},{"__type__":"cc.SpriteFrame","content":{"name":"img_pingmin","texture":"1bd5721b3","rect":[3,3,211,298],"offset":[-0.5,0],"originalSize":[212,298],"rotated":1,"capInsets":[0,0,0,0]}},{"__type__":"cc.SpriteFrame","content":{"name":"img_ltjl_gray","texture":"1994e2620","rect":[193,145,60,184],"offset":[0,0],"originalSize":[60,184],"rotated":1,"capInsets":[0,0,0,0]}},{"__type__":"cc.SpriteFrame","content":{"name":"img_oneday","texture":"1994e2620","rect":[3,539,168,168],"offset":[0,0],"originalSize":[168,168],"capInsets":[0,0,0,0]}},[{"__type__":"cc.Prefab","_name":"LRSGameView","data":{"__id__":1}},{"__type__":"cc.Node","_name":"LRSGameView","_children":[{"__id__":2},{"__id__":3},{"__id__":4},{"__id__":5},{"__id__":6},{"__id__":49},{"__id__":50},{"__id__":82}],"_components":[{"__type__":"b9fe8sZOKxAD7ZuVFQ5uGip","node":{"__id__":1},"GameView":{"__id__":109}},{"__id__":109},{"__type__":"cc.Widget","node":{"__id__":1},"_alignFlags":45,"_originalWidth":1280,"_originalHeight":720}],"_prefab":{"__type__":"cc.PrefabInfo","root":{"__id__":1},"asset":{"__uuid__":"b4srmF86tNvI2ufV08B/aK"},"fileId":"b1Y+ithbxPyLH2fcieiQnq"},"_contentSize":{"__type__":"cc.Size","width":1280,"height":720},"_trs":{"__type__":"TypedArray","ctor":"Float64Array","array":[640,360,0,0,0,0,1,1,1,1]}},{"__type__":"cc.Node","_name":"cancel","_parent":{"__id__":1},"_components":[{"__type__":"cc.Button","node":{"__id__":2},"_N$normalColor":{"__type__":"cc.Color","r":230,"g":230,"b":230},"_N$pressedColor":{"__type__":"cc.Color","r":200,"g":200,"b":200},"pressedColor":{"__type__":"cc.Color","r":200,"g":200,"b":200},"_N$disabledColor":{"__type__":"cc.Color","r":120,"g":120,"b":120,"a":200},"_N$normalSprite":{"__uuid__":"f0BIwQ8D5Ml7nTNQbh1YlS"},"_N$pressedSprite":{"__uuid__":"e97GVMl6JHh5Ml5qEDdSGa"},"pressedSprite":{"__uuid__":"e97GVMl6JHh5Ml5qEDdSGa"},"_N$hoverSprite":{"__uuid__":"f0BIwQ8D5Ml7nTNQbh1YlS"},"hoverSprite":{"__uuid__":"f0BIwQ8D5Ml7nTNQbh1YlS"},"_N$disabledSprite":{"__uuid__":"29FYIk+N1GYaeWH/q1NxQO"},"_N$target":{"__id__":2}},{"__type__":"cc.Widget","node":{"__id__":2},"_alignFlags":45,"_originalWidth":1280,"_originalHeight":500}],"_prefab":{"__type__":"cc.PrefabInfo","root":{"__id__":1},"asset":{"__uuid__":"b4srmF86tNvI2ufV08B/aK"},"fileId":"e2jb8FdnVK1Zw3wB7J9gyX"},"_contentSize":{"__type__":"cc.Size","width":1280,"height":720},"_trs":{"__type__":"TypedArray","ctor":"Float64Array","array":[0,0,0,0,0,0,1,1,1,1]}},{"__type__":"cc.Node","_name":"bg","_parent":{"__id__":1},"_components":[{"__type__":"cc.Sprite","node":{"__id__":3},"_materials":[{"__uuid__":"ecpdLyjvZBwrvm+cedCcQy"}],"_spriteFrame":{"__uuid__":"85+fUzEVFIEIstoxjme0zP"},"_sizeMode":0}],"_prefab":{"__type__":"cc.PrefabInfo","root":{"__id__":1},"asset":{"__uuid__":"b4srmF86tNvI2ufV08B/aK"},"fileId":"75BMrH9UtNMbilC5EcmahE"},"_contentSize":{"__type__":"cc.Size","width":1559,"height":720},"_trs":{"__type__":"TypedArray","ctor":"Float64Array","array":[0,0,0,0,0,0,1,1,1,1]}},{"__type__":"cc.Node","_name":"bg3","_parent":{"__id__":1},"_active":false,"_components":[{"__type__":"cc.Sprite","node":{"__id__":4},"_materials":[{"__uuid__":"ecpdLyjvZBwrvm+cedCcQy"}],"_spriteFrame":{"__uuid__":"620lbJP0FKpq/ouzXcwk0i"},"_sizeMode":0}],"_prefab":{"__type__":"cc.PrefabInfo","root":{"__id__":1},"asset":{"__uuid__":"b4srmF86tNvI2ufV08B/aK"},"fileId":"8d9cadq7tD8pRPGBzU9cnM"},"_contentSize":{"__type__":"cc.Size","width":1559,"height":643},"_trs":{"__type__":"TypedArray","ctor":"Float64Array","array":[0,-38,0,0,0,0,1,1,1,1]}},{"__type__":"cc.Node","_name":"bg2","_parent":{"__id__":1},"_components":[{"__type__":"cc.Sprite","node":{"__id__":5},"_materials":[{"__uuid__":"ecpdLyjvZBwrvm+cedCcQy"}],"_spriteFrame":{"__uuid__":"73AXmk1HxNB7YRNJreI8ny"},"_sizeMode":0}],"_prefab":{"__type__":"cc.PrefabInfo","root":{"__id__":1},"asset":{"__uuid__":"b4srmF86tNvI2ufV08B/aK"},"fileId":"2cSsOw1OFObbOrs2GQpG7G"},"_opacity":0,"_contentSize":{"__type__":"cc.Size","width":1559,"height":720},"_trs":{"__type__":"TypedArray","ctor":"Float64Array","array":[0,0,0,0,0,0,1,1,1,1]}},{"__type__":"cc.Node","_name":"node_center","_parent":{"__id__":1},"_children":[{"__type__":"cc.Node","_name":"node_gold","_parent":{"__id__":6},"_prefab":{"__type__":"cc.PrefabInfo","root":{"__id__":1},"asset":{"__uuid__":"b4srmF86tNvI2ufV08B/aK"},"fileId":"a87Xp0165MoLUb8H2hiCKi"},"_trs":{"__type__":"TypedArray","ctor":"Float64Array","array":[0,0,0,0,0,0,1,1,1,1]}},{"__id__":7},{"__id__":9},{"__id__":10},{"__id__":11},{"__id__":28},{"__id__":33},{"__id__":39}],"_components":[{"__id__":48},{"__type__":"cc.Widget","node":{"__id__":6},"_alignFlags":45,"_originalWidth":1280,"_originalHeight":720}],"_prefab":{"__type__":"cc.PrefabInfo","root":{"__id__":1},"asset":{"__uuid__":"b4srmF86tNvI2ufV08B/aK"},"fileId":"85HSci1PhMh6RGOzbcAtIy"},"_contentSize":{"__type__":"cc.Size","width":1280,"height":720},"_trs":{"__type__":"TypedArray","ctor":"Float64Array","array":[0,0,0,0,0,0,1,1,1,1]}},{"__type__":"cc.Node","_name":"btn_start","_parent":{"__id__":6},"_children":[{"__id__":8}],"_active":false,"_components":[{"__type__":"cc.Button","node":{"__id__":7},"zoomScale":0.9,"_N$transition":3,"transition":3,"_N$normalColor":{"__type__":"cc.Color","r":230,"g":230,"b":230},"_N$pressedColor":{"__type__":"cc.Color","r":200,"g":200,"b":200},"pressedColor":{"__type__":"cc.Color","r":200,"g":200,"b":200},"_N$disabledColor":{"__type__":"cc.Color","r":120,"g":120,"b":120,"a":200},"_N$normalSprite":{"__uuid__":"f0BIwQ8D5Ml7nTNQbh1YlS"},"_N$pressedSprite":{"__uuid__":"e97GVMl6JHh5Ml5qEDdSGa"},"pressedSprite":{"__uuid__":"e97GVMl6JHh5Ml5qEDdSGa"},"_N$hoverSprite":{"__uuid__":"f0BIwQ8D5Ml7nTNQbh1YlS"},"hoverSprite":{"__uuid__":"f0BIwQ8D5Ml7nTNQbh1YlS"},"_N$disabledSprite":{"__uuid__":"29FYIk+N1GYaeWH/q1NxQO"},"_N$target":{"__id__":7}},{"__type__":"cc.Widget","node":{"__id__":7},"_alignFlags":45,"_left":540,"_right":540,"_top":432,"_bottom":198,"_originalWidth":200,"_originalHeight":90}],"_prefab":{"__type__":"cc.PrefabInfo","root":{"__id__":1},"asset":{"__uuid__":"b4srmF86tNvI2ufV08B/aK"},"fileId":"cb04EJME5IUpHkzr1eGlE1"},"_contentSize":{"__type__":"cc.Size","width":200,"height":90},"_trs":{"__type__":"TypedArray","ctor":"Float64Array","array":[0,-117,0,0,0,0,1,1,1,1]}},{"__type__":"cc.Node","_name":"font_ksyx","_parent":{"__id__":7},"_components":[{"__type__":"cc.Sprite","node":{"__id__":8},"_materials":[{"__uuid__":"ecpdLyjvZBwrvm+cedCcQy"}],"_spriteFrame":{"__uuid__":"0bIOYcGzxN5Jt2zL2Lh4gu"},"_sizeMode":2,"_isTrimmedMode":false}],"_prefab":{"__type__":"cc.PrefabInfo","root":{"__id__":1},"asset":{"__uuid__":"b4srmF86tNvI2ufV08B/aK"},"fileId":"7aoPF42fJJt7qbtbj3h8m2"},"_contentSize":{"__type__":"cc.Size","width":262,"height":80},"_trs":{"__type__":"TypedArray","ctor":"Float64Array","array":[0,-4,0,0,0,0,1,1,1,1]}},{"__type__":"cc.Node","_name":"user_left","_parent":{"__id__":6},"_components":[{"__type__":"cc.Sprite","node":{"__id__":9},"_materials":[{"__uuid__":"ecpdLyjvZBwrvm+cedCcQy"}],"_type":1,"_sizeMode":0},{"__type__":"cc.Layout","node":{"__id__":9},"_layoutSize":{"__type__":"cc.Size","width":285,"height":520},"_resize":2,"_N$layoutType":2},{"__type__":"cc.Widget","node":{"__id__":9},"_alignFlags":13,"_top":115,"_bottom":85,"_originalHeight":550}],"_prefab":{"__type__":"cc.PrefabInfo","root":{"__id__":1},"asset":{"__uuid__":"b4srmF86tNvI2ufV08B/aK"},"fileId":"88q7uVjCdBqb49kFDnSlH0"},"_contentSize":{"__type__":"cc.Size","width":285,"height":520},"_anchorPoint":{"__type__":"cc.Vec2","x":0.5,"y":1},"_trs":{"__type__":"TypedArray","ctor":"Float64Array","array":[-497.5,245,0,0,0,0,1,1,1,1]}},{"__type__":"cc.Node","_name":"user_right","_parent":{"__id__":6},"_components":[{"__type__":"cc.Sprite","node":{"__id__":10},"_materials":[{"__uuid__":"ecpdLyjvZBwrvm+cedCcQy"}],"_type":1,"_sizeMode":0},{"__type__":"cc.Layout","node":{"__id__":10},"_layoutSize":{"__type__":"cc.Size","width":285,"height":350},"_resize":2,"_N$layoutType":2},{"__type__":"cc.Widget","node":{"__id__":10},"_alignFlags":37,"_top":115,"_bottom":255,"_originalHeight":350}],"_prefab":{"__type__":"cc.PrefabInfo","root":{"__id__":1},"asset":{"__uuid__":"b4srmF86tNvI2ufV08B/aK"},"fileId":"e7Hi2OgqdBe6jThzipP5d1"},"_contentSize":{"__type__":"cc.Size","width":285,"height":350},"_anchorPoint":{"__type__":"cc.Vec2","x":0.5,"y":1},"_trs":{"__type__":"TypedArray","ctor":"Float64Array","array":[497.5,245,0,0,0,0,1,1,1,1]}},{"__type__":"cc.Node","_name":"node_top_title","_parent":{"__id__":6},"_children":[{"__id__":12},{"__id__":13},{"__id__":14},{"__id__":15},{"__id__":19},{"__id__":24}],"_active":false,"_components":[{"__type__":"cc.Widget","node":{"__id__":11},"_alignFlags":41,"_left":640,"_right":640}],"_prefab":{"__type__":"cc.PrefabInfo","root":{"__id__":1},"asset":{"__uuid__":"b4srmF86tNvI2ufV08B/aK"},"fileId":"d9422FQcdF7ptTxuiO7kWc"},"_trs":{"__type__":"TypedArray","ctor":"Float64Array","array":[0,360,0,0,0,0,1,1,1,1]}},{"__type__":"cc.Node","_name":"yueliang","_parent":{"__id__":11},"_active":false,"_components":[{"__type__":"cc.Sprite","node":{"__id__":12},"_materials":[{"__uuid__":"ecpdLyjvZBwrvm+cedCcQy"}],"_spriteFrame":{"__uuid__":"11d75fGvFKAI4vrcRkD4wu"}}],"_prefab":{"__type__":"cc.PrefabInfo","root":{"__id__":1},"asset":{"__uuid__":"b4srmF86tNvI2ufV08B/aK"},"fileId":"864kcBPzNK56XtmsmQyMjN"},"_contentSize":{"__type__":"cc.Size","width":121,"height":119},"_trs":{"__type__":"TypedArray","ctor":"Float64Array","array":[-69.599,-120.856,0,0,0,0,1,1,1,1]}},{"__type__":"cc.Node","_name":"bg","_parent":{"__id__":11},"_components":[{"__type__":"cc.Sprite","node":{"__id__":13},"_materials":[{"__uuid__":"ecpdLyjvZBwrvm+cedCcQy"}],"_spriteFrame":{"__uuid__":"4f03VeM+5ElaitpQgaYbpE"},"_sizeMode":2,"_isTrimmedMode":false}],"_prefab":{"__type__":"cc.PrefabInfo","root":{"__id__":1},"asset":{"__uuid__":"b4srmF86tNvI2ufV08B/aK"},"fileId":"c77bpo9VVCmZgOmIMOa4J1"},"_contentSize":{"__type__":"cc.Size","width":602,"height":115},"_trs":{"__type__":"TypedArray","ctor":"Float64Array","array":[0,-57,0,0,0,0,1,1,1,1]}},{"__type__":"cc.Node","_name":"icon_dayornight","_parent":{"__id__":11},"_components":[{"__type__":"cc.Sprite","node":{"__id__":14},"_materials":[{"__uuid__":"ecpdLyjvZBwrvm+cedCcQy"}],"_spriteFrame":{"__uuid__":"b1NYoIBkNJcLXET4AfoQMj"}}],"_prefab":{"__type__":"cc.PrefabInfo","root":{"__id__":1},"asset":{"__uuid__":"b4srmF86tNvI2ufV08B/aK"},"fileId":"d9I9D5VGxDA4HB9k+8LoAf"},"_contentSize":{"__type__":"cc.Size","width":167,"height":164},"_trs":{"__type__":"TypedArray","ctor":"Float64Array","array":[0,0,0,0,0,0,1,1,1,1]}},{"__type__":"cc.Node","_name":"djs_tips","_parent":{"__id__":11},"_children":[{"__id__":16}],"_components":[{"__type__":"cc.Label","node":{"__id__":15},"_materials":[{"__uuid__":"ecpdLyjvZBwrvm+cedCcQy"}],"_useOriginalSize":false,"_string":"倒计时","_N$string":"倒计时","_fontSize":24,"_lineHeight":24,"_N$file":{"__uuid__":"077ozJbA1P0oN2tphywD7U"},"_isSystemFontUsed":false,"_N$horizontalAlign":1,"_N$verticalAlign":1},{"__id__":18}],"_prefab":{"__type__":"cc.PrefabInfo","root":{"__id__":1},"asset":{"__uuid__":"b4srmF86tNvI2ufV08B/aK"},"fileId":"f3SgBhxEBFJrsdYCv59oi0"},"_color":{"__type__":"cc.Color","r":230,"g":228,"b":220},"_contentSize":{"__type__":"cc.Size","width":72,"height":30.24},"_trs":{"__type__":"TypedArray","ctor":"Float64Array","array":[-200,-36,0,0,0,0,1,1,1,1]}},{"__type__":"cc.Node","_name":"times","_parent":{"__id__":15},"_components":[{"__id__":17}],"_prefab":{"__type__":"cc.PrefabInfo","root":{"__id__":1},"asset":{"__uuid__":"b4srmF86tNvI2ufV08B/aK"},"fileId":"abgEfpdwhD5oiINRB8ANP6"},"_contentSize":{"__type__":"cc.Size","width":18,"height":20},"_trs":{"__type__":"TypedArray","ctor":"Float64Array","array":[55,1,0,0,0,0,1,1,1,1]}},{"__type__":"cc.Label","node":{"__id__":16},"_materials":[{"__uuid__":"ecpdLyjvZBwrvm+cedCcQy"}],"_useOriginalSize":false,"_string":"15","_N$string":"15","_lineHeight":20,"_N$file":{"__uuid__":"f6UIMKHkhPbIau9IPiOkX/"},"_isSystemFontUsed":false,"_N$horizontalAlign":1},{"__type__":"b4d96hVlY9B5pO1ATgGerv1","node":{"__id__":15},"time_num":{"__id__":17}},{"__type__":"cc.Node","_name":"day","_parent":{"__id__":11},"_children":[{"__id__":20},{"__id__":21},{"__id__":23}],"_prefab":{"__type__":"cc.PrefabInfo","root":{"__id__":1},"asset":{"__uuid__":"b4srmF86tNvI2ufV08B/aK"},"fileId":"c2pK9OrA5MAbgp3lrJCv/i"},"_trs":{"__type__":"TypedArray","ctor":"Float64Array","array":[184,-36,0,0,0,0,1,1,1,1]}},{"__type__":"cc.Node","_name":"text_bai","_parent":{"__id__":19},"_components":[{"__type__":"cc.Sprite","node":{"__id__":20},"_materials":[{"__uuid__":"ecpdLyjvZBwrvm+cedCcQy"}],"_spriteFrame":{"__uuid__":"e9ohnDDN5DFIARkiIDp8TP"}}],"_prefab":{"__type__":"cc.PrefabInfo","root":{"__id__":1},"asset":{"__uuid__":"b4srmF86tNvI2ufV08B/aK"},"fileId":"daBSe60jpC+JWMPf45flNF"},"_contentSize":{"__type__":"cc.Size","width":62,"height":23},"_trs":{"__type__":"TypedArray","ctor":"Float64Array","array":[0,0,0,0,0,0,1,1,1,1]}},{"__type__":"cc.Node","_name":"txt_bai","_parent":{"__id__":19},"_components":[{"__id__":22}],"_prefab":{"__type__":"cc.PrefabInfo","root":{"__id__":1},"asset":{"__uuid__":"b4srmF86tNvI2ufV08B/aK"},"fileId":"e9bZr0SvFC6IWaunqk6Buc"},"_contentSize":{"__type__":"cc.Size","width":6,"height":20},"_trs":{"__type__":"TypedArray","ctor":"Float64Array","array":[0,0,0,0,0,0,1,1,1,1]}},{"__type__":"cc.Label","node":{"__id__":21},"_materials":[{"__uuid__":"ecpdLyjvZBwrvm+cedCcQy"}],"_useOriginalSize":false,"_string":"1","_N$string":"1","_lineHeight":20,"_N$file":{"__uuid__":"f6UIMKHkhPbIau9IPiOkX/"},"_isSystemFontUsed":false,"_N$horizontalAlign":1},{"__type__":"cc.Node","_name":"guang","_parent":{"__id__":19},"_components":[{"__type__":"sp.Skeleton","node":{"__id__":23},"_materials":[{"__uuid__":"7a/QZLET9IDreTiBfRn2PD"}],"defaultAnimation":"animation","_preCacheMode":0,"_animationName":"animation","_N$skeletonData":{"__uuid__":"76koQsU8dET5vqPJ/Pxdj6"}}],"_prefab":{"__type__":"cc.PrefabInfo","root":{"__id__":1},"asset":{"__uuid__":"b4srmF86tNvI2ufV08B/aK"},"fileId":"483Tvsz8ZNErBxK5U7nMqB"},"_contentSize":{"__type__":"cc.Size","width":255.39,"height":642.73},"_trs":{"__type__":"TypedArray","ctor":"Float64Array","array":[-198.116,-335.209,0,0,0,0,1,1,1,1]}},{"__type__":"cc.Node","_name":"night","_parent":{"__id__":11},"_children":[{"__id__":25},{"__id__":26}],"_active":false,"_prefab":{"__type__":"cc.PrefabInfo","root":{"__id__":1},"asset":{"__uuid__":"b4srmF86tNvI2ufV08B/aK"},"fileId":"c7mjijjwVKK4qltNWj3uBc"},"_trs":{"__type__":"TypedArray","ctor":"Float64Array","array":[184,-36,0,0,0,0,1,1,1,1]}},{"__type__":"cc.Node","_name":"text_wan","_parent":{"__id__":24},"_components":[{"__type__":"cc.Sprite","node":{"__id__":25},"_materials":[{"__uuid__":"ecpdLyjvZBwrvm+cedCcQy"}],"_spriteFrame":{"__uuid__":"03D4/pLC1I7btIcqwzAaE+"}}],"_prefab":{"__type__":"cc.PrefabInfo","root":{"__id__":1},"asset":{"__uuid__":"b4srmF86tNvI2ufV08B/aK"},"fileId":"3eMF/7FDZJBr+QqalO8KN9"},"_contentSize":{"__type__":"cc.Size","width":62,"height":23},"_trs":{"__type__":"TypedArray","ctor":"Float64Array","array":[0,0,0,0,0,0,1,1,1,1]}},{"__type__":"cc.Node","_name":"txt_wan","_parent":{"__id__":24},"_components":[{"__id__":27}],"_prefab":{"__type__":"cc.PrefabInfo","root":{"__id__":1},"asset":{"__uuid__":"b4srmF86tNvI2ufV08B/aK"},"fileId":"f8V9dSNFREVKyHOKXMaEI6"},"_contentSize":{"__type__":"cc.Size","width":6,"height":20},"_trs":{"__type__":"TypedArray","ctor":"Float64Array","array":[0,0,0,0,0,0,1,1,1,1]}},{"__type__":"cc.Label","node":{"__id__":26},"_materials":[{"__uuid__":"ecpdLyjvZBwrvm+cedCcQy"}],"_useOriginalSize":false,"_string":"1","_N$string":"1","_lineHeight":20,"_N$file":{"__uuid__":"41Q0FKMo1MEaPlCpVjTykm"},"_isSystemFontUsed":false,"_N$horizontalAlign":1},{"__type__":"cc.Node","_name":"game_record","_parent":{"__id__":6},"_children":[{"__id__":29},{"__id__":30}],"_active":false,"_prefab":{"__type__":"cc.PrefabInfo","root":{"__id__":1},"asset":{"__uuid__":"b4srmF86tNvI2ufV08B/aK"},"fileId":"be3GbXB8BCda3BP+SPCG8Q"},"_trs":{"__type__":"TypedArray","ctor":"Float64Array","array":[0,0,0,0,0,0,1,1,1,1]}},{"__type__":"cc.Node","_name":"bg","_parent":{"__id__":28},"_components":[{"__type__":"cc.Sprite","node":{"__id__":29},"_materials":[{"__uuid__":"ecpdLyjvZBwrvm+cedCcQy"}],"_spriteFrame":{"__uuid__":"43VTEGPWxMjrMm9lH12JTM"}}],"_prefab":{"__type__":"cc.PrefabInfo","root":{"__id__":1},"asset":{"__uuid__":"b4srmF86tNvI2ufV08B/aK"},"fileId":"a3bIqt/hhGfpNM89vBegtm"},"_contentSize":{"__type__":"cc.Size","width":726,"height":444},"_trs":{"__type__":"TypedArray","ctor":"Float64Array","array":[0,0,0,0,0,0,1,1,1,1]}},{"__type__":"cc.Node","_name":"scrollview","_parent":{"__id__":28},"_children":[{"__id__":31}],"_components":[{"__type__":"cc.Sprite","node":{"__id__":30},"_materials":[{"__uuid__":"ecpdLyjvZBwrvm+cedCcQy"}],"_type":1,"_sizeMode":0},{"__type__":"cc.ScrollView","node":{"__id__":30},"horizontal":false,"brake":0.75,"bounceDuration":0.23,"_N$content":{"__id__":32},"content":{"__id__":32},"_N$horizontalScrollBar":null,"_N$verticalScrollBar":null}],"_prefab":{"__type__":"cc.PrefabInfo","root":{"__id__":1},"asset":{"__uuid__":"b4srmF86tNvI2ufV08B/aK"},"fileId":"6fnML03ZZETbuXC7CZQNwt"},"_contentSize":{"__type__":"cc.Size","width":480,"height":340},"_trs":{"__type__":"TypedArray","ctor":"Float64Array","array":[0,-4,0,0,0,0,1,1,1,1]}},{"__type__":"cc.Node","_name":"view","_parent":{"__id__":30},"_children":[{"__id__":32}],"_components":[{"__type__":"cc.Mask","node":{"__id__":31},"_materials":[{"__uuid__":"ecpdLyjvZBwrvm+cedCcQy"}],"_N$alphaThreshold":0}],"_prefab":{"__type__":"cc.PrefabInfo","root":{"__id__":1},"asset":{"__uuid__":"b4srmF86tNvI2ufV08B/aK"},"fileId":"10215ru0xAuJvpGHGum1mz"},"_contentSize":{"__type__":"cc.Size","width":480,"height":340},"_trs":{"__type__":"TypedArray","ctor":"Float64Array","array":[0,0,0,0,0,0,1,1,1,1]}},{"__type__":"cc.Node","_name":"content","_parent":{"__id__":31},"_components":[{"__type__":"cc.Layout","node":{"__id__":32},"_layoutSize":{"__type__":"cc.Size","width":480,"height":40},"_resize":1,"_N$layoutType":2}],"_prefab":{"__type__":"cc.PrefabInfo","root":{"__id__":1},"asset":{"__uuid__":"b4srmF86tNvI2ufV08B/aK"},"fileId":"36s2qWVx5Bv4pKjzLSUchG"},"_contentSize":{"__type__":"cc.Size","width":480,"height":40},"_anchorPoint":{"__type__":"cc.Vec2","x":0.5,"y":1},"_trs":{"__type__":"TypedArray","ctor":"Float64Array","array":[0,170,0,0,0,0,1,1,1,1]}},{"__type__":"cc.Node","_name":"node_action","_parent":{"__id__":6},"_children":[{"__id__":34},{"__id__":35},{"__id__":36},{"__id__":37},{"__id__":38}],"_active":false,"_components":[{"__type__":"cc.Widget","node":{"__id__":33},"_alignFlags":45,"_left":640,"_right":640,"_top":360,"_bottom":360}],"_prefab":{"__type__":"cc.PrefabInfo","root":{"__id__":1},"asset":{"__uuid__":"b4srmF86tNvI2ufV08B/aK"},"fileId":"209OJKMvtJTJJE8EmCcq4z"},"_trs":{"__type__":"TypedArray","ctor":"Float64Array","array":[0,0,0,0,0,0,1,1,1,1]}},{"__type__":"cc.Node","_name":"bg","_parent":{"__id__":33},"_components":[{"__type__":"cc.Sprite","node":{"__id__":34},"_materials":[{"__uuid__":"ecpdLyjvZBwrvm+cedCcQy"}],"_spriteFrame":{"__uuid__":"43VTEGPWxMjrMm9lH12JTM"},"_sizeMode":2,"_isTrimmedMode":false},{"__type__":"cc.BlockInputEvents","node":{"__id__":34}}],"_prefab":{"__type__":"cc.PrefabInfo","root":{"__id__":1},"asset":{"__uuid__":"b4srmF86tNvI2ufV08B/aK"},"fileId":"f0XqwyxMhEALCEaaQJWCNy"},"_contentSize":{"__type__":"cc.Size","width":726,"height":444},"_trs":{"__type__":"TypedArray","ctor":"Float64Array","array":[0,0,0,0,0,0,1,1,1,1]}},{"__type__":"cc.Node","_name":"icon2","_parent":{"__id__":33},"_components":[{"__type__":"cc.Sprite","node":{"__id__":35},"_materials":[{"__uuid__":"ecpdLyjvZBwrvm+cedCcQy"}],"_spriteFrame":{"__uuid__":"e0XNhHCDNEw7iG0TQDY/3s"},"_sizeMode":2,"_isTrimmedMode":false}],"_prefab":{"__type__":"cc.PrefabInfo","root":{"__id__":1},"asset":{"__uuid__":"b4srmF86tNvI2ufV08B/aK"},"fileId":"08f6LnEYVIfaB8Dho6hAc+"},"_contentSize":{"__type__":"cc.Size","width":170,"height":238},"_trs":{"__type__":"TypedArray","ctor":"Float64Array","array":[180,1,0,0,0,0,1,1,1,1]}},{"__type__":"cc.Node","_name":"icon1","_parent":{"__id__":33},"_components":[{"__type__":"cc.Sprite","node":{"__id__":36},"_materials":[{"__uuid__":"ecpdLyjvZBwrvm+cedCcQy"}],"_spriteFrame":{"__uuid__":"3dQ8dItJpJHrW2V9116svk"},"_sizeMode":2,"_isTrimmedMode":false}],"_prefab":{"__type__":"cc.PrefabInfo","root":{"__id__":1},"asset":{"__uuid__":"b4srmF86tNvI2ufV08B/aK"},"fileId":"c6cmTofv1GqZt2f7uyRAz4"},"_contentSize":{"__type__":"cc.Size","width":170,"height":238},"_trs":{"__type__":"TypedArray","ctor":"Float64Array","array":[-180,1,0,0,0,0,1,1,1,1]}},{"__type__":"cc.Node","_name":"icon3","_parent":{"__id__":33},"_components":[{"__type__":"cc.Sprite","node":{"__id__":37},"_materials":[{"__uuid__":"ecpdLyjvZBwrvm+cedCcQy"}],"_spriteFrame":{"__uuid__":"1a7sjTXfhGoIvahkhesXRl"},"_sizeMode":2,"_isTrimmedMode":false}],"_prefab":{"__type__":"cc.PrefabInfo","root":{"__id__":1},"asset":{"__uuid__":"b4srmF86tNvI2ufV08B/aK"},"fileId":"19CMtn0udJjoQiJ8px1Zd3"},"_contentSize":{"__type__":"cc.Size","width":170,"height":238},"_trs":{"__type__":"TypedArray","ctor":"Float64Array","array":[0,1,0,0,0,0,1,1,1,1]}},{"__type__":"cc.Node","_name":"icon4","_parent":{"__id__":33},"_active":false,"_components":[{"__type__":"cc.Sprite","node":{"__id__":38},"_materials":[{"__uuid__":"ecpdLyjvZBwrvm+cedCcQy"}],"_spriteFrame":{"__uuid__":"94LqBG+pRDLpyTlREDI0vJ"},"_sizeMode":0,"_isTrimmedMode":false}],"_prefab":{"__type__":"cc.PrefabInfo","root":{"__id__":1},"asset":{"__uuid__":"b4srmF86tNvI2ufV08B/aK"},"fileId":"d6YFNVc8NJgYMgy+1CEbu9"},"_contentSize":{"__type__":"cc.Size","width":170,"height":238},"_trs":{"__type__":"TypedArray","ctor":"Float64Array","array":[0,1,0,0,0,0,1,1,1,1]}},{"__type__":"cc.Node","_name":"node_spine","_parent":{"__id__":6},"_children":[{"__id__":40},{"__id__":42},{"__id__":44},{"__id__":46}],"_components":[{"__type__":"8a1c5/w6zJDkKvpcjf3KCSI","node":{"__id__":39},"langrenSp":{"__id__":41},"lierenSp":{"__id__":43},"nvwuduSp":{"__id__":45},"nvwujiuSp":{"__id__":47},"user_node":{"__uuid__":"c6XjLEYkpJOqJw5wEb61Gv"}}],"_prefab":{"__type__":"cc.PrefabInfo","root":{"__id__":1},"asset":{"__uuid__":"b4srmF86tNvI2ufV08B/aK"},"fileId":"14s1ZICPhPf5zihQVY6+Q7"},"_trs":{"__type__":"TypedArray","ctor":"Float64Array","array":[0,0,0,0,0,0,1,1,1,1]}},{"__type__":"cc.Node","_name":"langren","_parent":{"__id__":39},"_active":false,"_components":[{"__id__":41}],"_prefab":{"__type__":"cc.PrefabInfo","root":{"__id__":1},"asset":{"__uuid__":"b4srmF86tNvI2ufV08B/aK"},"fileId":"d1jOX+IsVNN4lCQEeR1FSF"},"_contentSize":{"__type__":"cc.Size","width":618,"height":505},"_trs":{"__type__":"TypedArray","ctor":"Float64Array","array":[1,-4,0,0,0,0,1,1,1,1]}},{"__type__":"sp.Skeleton","node":{"__id__":40},"_materials":[{"__uuid__":"7a/QZLET9IDreTiBfRn2PD"}],"defaultAnimation":"animation","_preCacheMode":0,"timeScale":0.25,"_animationName":"animation","_N$skeletonData":{"__uuid__":"7fFyT5a1BCk7KJQ7yHk2a0"}},{"__type__":"cc.Node","_name":"lieren","_parent":{"__id__":39},"_active":false,"_components":[{"__id__":43}],"_prefab":{"__type__":"cc.PrefabInfo","root":{"__id__":1},"asset":{"__uuid__":"b4srmF86tNvI2ufV08B/aK"},"fileId":"d8Oa1BfWlF/6Pl5o+uEszS"},"_contentSize":{"__type__":"cc.Size","width":599,"height":515},"_trs":{"__type__":"TypedArray","ctor":"Float64Array","array":[-2,-22,0,0,0,0,1,1,1,1]}},{"__type__":"sp.Skeleton","node":{"__id__":42},"_materials":[{"__uuid__":"7a/QZLET9IDreTiBfRn2PD"}],"defaultAnimation":"animation","_preCacheMode":0,"timeScale":0.25,"_animationName":"animation","_N$skeletonData":{"__uuid__":"72bgzgEJ9E6J1LKV+w7r15"},"_N$enableBatch":true},{"__type__":"cc.Node","_name":"nvwudu","_parent":{"__id__":39},"_active":false,"_components":[{"__id__":45}],"_prefab":{"__type__":"cc.PrefabInfo","root":{"__id__":1},"asset":{"__uuid__":"b4srmF86tNvI2ufV08B/aK"},"fileId":"5eMW3tMy9BfImLfLPOOYUe"},"_contentSize":{"__type__":"cc.Size","width":584,"height":507},"_trs":{"__type__":"TypedArray","ctor":"Float64Array","array":[-7,17,0,0,0,0,1,1,1,1]}},{"__type__":"sp.Skeleton","node":{"__id__":44},"_materials":[{"__uuid__":"7a/QZLET9IDreTiBfRn2PD"}],"defaultAnimation":"animation","_preCacheMode":0,"timeScale":0.25,"_animationName":"animation","_N$skeletonData":{"__uuid__":"d8/GdSi7VAbKk04UUQU1ft"}},{"__type__":"cc.Node","_name":"nvwujiu","_parent":{"__id__":39},"_active":false,"_components":[{"__id__":47}],"_prefab":{"__type__":"cc.PrefabInfo","root":{"__id__":1},"asset":{"__uuid__":"b4srmF86tNvI2ufV08B/aK"},"fileId":"bb1nwcTNhHEIVetYEbVewQ"},"_contentSize":{"__type__":"cc.Size","width":598.66,"height":607.01},"_trs":{"__type__":"TypedArray","ctor":"Float64Array","array":[-7,16,0,0,0,0,1,1,1,1]}},{"__type__":"sp.Skeleton","node":{"__id__":46},"_materials":[{"__uuid__":"7a/QZLET9IDreTiBfRn2PD"}],"defaultAnimation":"animation","_preCacheMode":0,"timeScale":0.25,"_animationName":"animation","_N$skeletonData":{"__uuid__":"a1lpakYPRAb4qmWedDPXKY"}},{"__type__":"a9cb7i+Ip1JoKG02TZ62yhH","node":{"__id__":6},"alarm_clock":{"__id__":18},"btn_start":{"__id__":7},"node_left":{"__id__":9},"node_right":{"__id__":10},"node_top":{"__id__":11},"node_spine":{"__id__":39},"node_action":{"__id__":33},"node_gametxt":{"__id__":28},"gametxt_item":{"__uuid__":"75MryyDkVN0oVU4N5IUw3M"},"node_userout":{"__uuid__":"80eo6srRZGr6J+SeGxr4yP"},"node_pingannight":{"__uuid__":"48CF6tOlZEt7S48AtJ1skk"},"user_item":{"__uuid__":"2bDbWPwDtL4ouVu04WmTIk"},"start_game":{"__uuid__":"83dYePJLhEDIhmHs4pFUVP"},"day_pre":{"__uuid__":"26o+UNU+5NOagiELAPJ3QF"},"night_pre":{"__uuid__":"4aeZxsYZ9HYITqHsg3M2Gy"},"userselect_pre":{"__uuid__":"1esdMhnThGsbl9c/GREe38"},"day_num":{"__id__":22},"night_num":{"__id__":27}},{"__type__":"cc.Node","_name":"UINode","_parent":{"__id__":1},"_prefab":{"__type__":"cc.PrefabInfo","root":{"__id__":1},"asset":{"__uuid__":"b4srmF86tNvI2ufV08B/aK"},"fileId":"35nbVJY4RLK48BNJRKNyKE"},"_trs":{"__type__":"TypedArray","ctor":"Float64Array","array":[0,0,0,0,0,0,1,1,1,1]}},{"__type__":"cc.Node","_name":"node_game_chat","_parent":{"__id__":1},"_children":[{"__id__":51},{"__id__":52},{"__id__":66},{"__id__":75},{"__id__":79}],"_active":false,"_components":[{"__id__":81},{"__type__":"cc.Widget","node":{"__id__":50},"_alignFlags":37,"_left":830,"_top":20,"_bottom":20,"_originalWidth":450,"_originalHeight":680}],"_prefab":{"__type__":"cc.PrefabInfo","root":{"__id__":1},"asset":{"__uuid__":"b4srmF86tNvI2ufV08B/aK"},"fileId":"5bl6yxRftFc7JG2Kak2IEP"},"_contentSize":{"__type__":"cc.Size","width":450,"height":680},"_trs":{"__type__":"TypedArray","ctor":"Float64Array","array":[415,0,0,0,0,0,1,1,1,1]}},{"__type__":"cc.Node","_name":"btn_click","_parent":{"__id__":50},"_active":false,"_components":[{"__type__":"cc.Button","node":{"__id__":51},"clickEvents":[{"__type__":"cc.ClickEvent","target":{"__id__":50},"_componentId":"eabccgP07FDrZeKfIIX9/Dw","handler":"onClickEvent","customEventData":"0"}],"_N$normalColor":{"__type__":"cc.Color","r":214,"g":214,"b":214},"_N$target":{"__id__":50}},{"__type__":"cc.Sprite","node":{"__id__":51},"_materials":[{"__uuid__":"ecpdLyjvZBwrvm+cedCcQy"}],"_spriteFrame":{"__uuid__":"69sxajTGhG8Y+U9MV9Ah2e"},"_sizeMode":0}],"_prefab":{"__type__":"cc.PrefabInfo","root":{"__id__":1},"asset":{"__uuid__":"b4srmF86tNvI2ufV08B/aK"},"fileId":"19qYXy9SJBzoFFhslzy2eL"},"_trs":{"__type__":"TypedArray","ctor":"Float64Array","array":[160,-300,0,0,0,0,1,1,1,1]}},{"__type__":"cc.Node","_name":"spr","_parent":{"__id__":50},"_children":[{"__id__":53}],"_components":[{"__type__":"cc.BlockInputEvents","node":{"__id__":52}}],"_prefab":{"__type__":"cc.PrefabInfo","root":{"__id__":1},"asset":{"__uuid__":"b4srmF86tNvI2ufV08B/aK"},"fileId":"afgpSugr1FEpzAfwxi1a6M"},"_contentSize":{"__type__":"cc.Size","width":450,"height":570},"_trs":{"__type__":"TypedArray","ctor":"Float64Array","array":[450,35,0,0,0,0,1,1,1,1]}},{"__type__":"cc.Node","_name":"panel","_parent":{"__id__":52},"_children":[{"__id__":54},{"__id__":57},{"__id__":60},{"__id__":63},{"__id__":64},{"__id__":65}],"_components":[{"__type__":"cc.Sprite","node":{"__id__":53},"_materials":[{"__uuid__":"ecpdLyjvZBwrvm+cedCcQy"}],"_spriteFrame":{"__uuid__":"17dDgWZ2ZP3Jn9Kgntmq8A"},"_sizeMode":0}],"_prefab":{"__type__":"cc.PrefabInfo","root":{"__id__":1},"asset":{"__uuid__":"b4srmF86tNvI2ufV08B/aK"},"fileId":"dfLKFBYiJJMY93Uo7zzCH7"},"_contentSize":{"__type__":"cc.Size","width":442,"height":610},"_trs":{"__type__":"TypedArray","ctor":"Float64Array","array":[0,0,0,0,0,0,1,1,1,1]}},{"__type__":"cc.Node","_name":"ScrollView1","_parent":{"__id__":53},"_children":[{"__id__":55}],"_components":[{"__type__":"cc.ScrollView","node":{"__id__":54},"horizontal":false,"brake":0.75,"bounceDuration":0.23,"_N$content":{"__id__":56},"content":{"__id__":56},"_N$horizontalScrollBar":null,"_N$verticalScrollBar":null}],"_prefab":{"__type__":"cc.PrefabInfo","root":{"__id__":1},"asset":{"__uuid__":"b4srmF86tNvI2ufV08B/aK"},"fileId":"2bT+5WCv9MrayvVexLhBc/"},"_contentSize":{"__type__":"cc.Size","width":320,"height":530},"_trs":{"__type__":"TypedArray","ctor":"Float64Array","array":[-19,0,0,0,0,0,1,1,1,1]}},{"__type__":"cc.Node","_name":"view","_parent":{"__id__":54},"_children":[{"__id__":56}],"_components":[{"__type__":"cc.Mask","node":{"__id__":55},"_materials":[{"__uuid__":"ecpdLyjvZBwrvm+cedCcQy"}],"_N$alphaThreshold":0},{"__type__":"cc.Widget","node":{"__id__":55},"_alignFlags":45,"_originalWidth":204,"_originalHeight":250}],"_prefab":{"__type__":"cc.PrefabInfo","root":{"__id__":1},"asset":{"__uuid__":"b4srmF86tNvI2ufV08B/aK"},"fileId":"20zoRGOoJH+pu6nAQEXKsR"},"_contentSize":{"__type__":"cc.Size","width":320,"height":530},"_trs":{"__type__":"TypedArray","ctor":"Float64Array","array":[0,0,0,0,0,0,1,1,1,1]}},{"__type__":"cc.Node","_name":"content","_parent":{"__id__":55},"_components":[{"__type__":"cc.Layout","node":{"__id__":56},"_layoutSize":{"__type__":"cc.Size","width":320,"height":74},"_resize":1,"_N$layoutType":2,"_N$paddingLeft":3,"_N$spacingY":5}],"_prefab":{"__type__":"cc.PrefabInfo","root":{"__id__":1},"asset":{"__uuid__":"b4srmF86tNvI2ufV08B/aK"},"fileId":"e3yG1SiLJKL7xnqkFugfzj"},"_contentSize":{"__type__":"cc.Size","width":320,"height":74},"_anchorPoint":{"__type__":"cc.Vec2","x":0.5,"y":1},"_trs":{"__type__":"TypedArray","ctor":"Float64Array","array":[0,265,0,0,0,0,1,1,1,1]}},{"__type__":"cc.Node","_name":"ScrollView2","_parent":{"__id__":53},"_children":[{"__id__":58}],"_components":[{"__type__":"cc.ScrollView","node":{"__id__":57},"horizontal":false,"brake":0.75,"bounceDuration":0.23,"_N$content":{"__id__":59},"content":{"__id__":59},"_N$horizontalScrollBar":null,"_N$verticalScrollBar":null}],"_prefab":{"__type__":"cc.PrefabInfo","root":{"__id__":1},"asset":{"__uuid__":"b4srmF86tNvI2ufV08B/aK"},"fileId":"97C0hGkwxHhZVvtuENII3S"},"_contentSize":{"__type__":"cc.Size","width":320,"height":530},"_trs":{"__type__":"TypedArray","ctor":"Float64Array","array":[-19,0,0,0,0,0,1,1,1,1]}},{"__type__":"cc.Node","_name":"view","_parent":{"__id__":57},"_children":[{"__id__":59}],"_components":[{"__type__":"cc.Mask","node":{"__id__":58},"_materials":[{"__uuid__":"ecpdLyjvZBwrvm+cedCcQy"}],"_N$alphaThreshold":0},{"__type__":"cc.Widget","node":{"__id__":58},"_alignFlags":45,"_originalWidth":204,"_originalHeight":250}],"_prefab":{"__type__":"cc.PrefabInfo","root":{"__id__":1},"asset":{"__uuid__":"b4srmF86tNvI2ufV08B/aK"},"fileId":"68D7sOG5lCFYQDFqV65KIq"},"_contentSize":{"__type__":"cc.Size","width":320,"height":530},"_trs":{"__type__":"TypedArray","ctor":"Float64Array","array":[0,0,0,0,0,0,1,1,1,1]}},{"__type__":"cc.Node","_name":"content","_parent":{"__id__":58},"_components":[{"__type__":"cc.Layout","node":{"__id__":59},"_layoutSize":{"__type__":"cc.Size","width":320,"height":50},"_resize":1,"_N$layoutType":3,"_N$paddingLeft":10,"_N$paddingTop":10,"_N$spacingX":20,"_N$spacingY":5}],"_prefab":{"__type__":"cc.PrefabInfo","root":{"__id__":1},"asset":{"__uuid__":"b4srmF86tNvI2ufV08B/aK"},"fileId":"b6ted2BM1JYJpfkm9ojYPd"},"_contentSize":{"__type__":"cc.Size","width":320,"height":50},"_anchorPoint":{"__type__":"cc.Vec2","x":0.5,"y":1},"_trs":{"__type__":"TypedArray","ctor":"Float64Array","array":[0,265,0,0,0,0,1,1,1,1]}},{"__type__":"cc.Node","_name":"ScrollView3","_parent":{"__id__":53},"_children":[{"__id__":61}],"_components":[{"__type__":"cc.ScrollView","node":{"__id__":60},"horizontal":false,"brake":0.75,"bounceDuration":0.23,"_N$content":{"__id__":62},"content":{"__id__":62},"_N$horizontalScrollBar":null,"_N$verticalScrollBar":null}],"_prefab":{"__type__":"cc.PrefabInfo","root":{"__id__":1},"asset":{"__uuid__":"b4srmF86tNvI2ufV08B/aK"},"fileId":"e3Mk8Z+dpJBp21jSO1lbC9"},"_contentSize":{"__type__":"cc.Size","width":320,"height":530},"_trs":{"__type__":"TypedArray","ctor":"Float64Array","array":[-19,0,0,0,0,0,1,1,1,1]}},{"__type__":"cc.Node","_name":"view","_parent":{"__id__":60},"_children":[{"__id__":62}],"_components":[{"__type__":"cc.Mask","node":{"__id__":61},"_materials":[{"__uuid__":"ecpdLyjvZBwrvm+cedCcQy"}],"_N$alphaThreshold":0},{"__type__":"cc.Widget","node":{"__id__":61},"_alignFlags":45,"_originalWidth":204,"_originalHeight":250}],"_prefab":{"__type__":"cc.PrefabInfo","root":{"__id__":1},"asset":{"__uuid__":"b4srmF86tNvI2ufV08B/aK"},"fileId":"3cfm35IyZNAbWMtJ4Hg4YA"},"_contentSize":{"__type__":"cc.Size","width":320,"height":530},"_trs":{"__type__":"TypedArray","ctor":"Float64Array","array":[0,0,0,0,0,0,1,1,1,1]}},{"__type__":"cc.Node","_name":"content","_parent":{"__id__":61},"_components":[{"__type__":"cc.Layout","node":{"__id__":62},"_layoutSize":{"__type__":"cc.Size","width":320,"height":50},"_resize":1,"_N$layoutType":2,"_N$paddingLeft":3,"_N$spacingY":5}],"_prefab":{"__type__":"cc.PrefabInfo","root":{"__id__":1},"asset":{"__uuid__":"b4srmF86tNvI2ufV08B/aK"},"fileId":"02rzwGAqJIA7FBr0nJeEDQ"},"_contentSize":{"__type__":"cc.Size","width":320,"height":50},"_anchorPoint":{"__type__":"cc.Vec2","x":0.5},"_trs":{"__type__":"TypedArray","ctor":"Float64Array","array":[0,265,0,0,0,0,1,1,1,1]}},{"__type__":"cc.Node","_name":"btn_chattxt","_parent":{"__id__":53},"_components":[{"__type__":"cc.Sprite","node":{"__id__":63},"_materials":[{"__uuid__":"ecpdLyjvZBwrvm+cedCcQy"}],"_spriteFrame":{"__uuid__":"2diFYJ4xJCNrXKzt56WsXv"}},{"__type__":"cc.Button","node":{"__id__":63},"clickEvents":[{"__type__":"cc.ClickEvent","target":{"__id__":50}}],"_N$transition":2,"transition":2,"_N$normalSprite":{"__uuid__":"2diFYJ4xJCNrXKzt56WsXv"},"_N$pressedSprite":{"__uuid__":"4cdqq7D69O+qjjhJDQzXxx"},"pressedSprite":{"__uuid__":"4cdqq7D69O+qjjhJDQzXxx"},"_N$hoverSprite":{"__uuid__":"2diFYJ4xJCNrXKzt56WsXv"},"hoverSprite":{"__uuid__":"2diFYJ4xJCNrXKzt56WsXv"},"_N$disabledSprite":{"__uuid__":"4cdqq7D69O+qjjhJDQzXxx"},"_N$target":{"__id__":63}}],"_prefab":{"__type__":"cc.PrefabInfo","root":{"__id__":1},"asset":{"__uuid__":"b4srmF86tNvI2ufV08B/aK"},"fileId":"6bceO6Pg1BWYPZwoBq5rIw"},"_contentSize":{"__type__":"cc.Size","width":60,"height":184},"_trs":{"__type__":"TypedArray","ctor":"Float64Array","array":[177,183,0,0,0,0,1,1,1,1]}},{"__type__":"cc.Node","_name":"btn_chatbq","_parent":{"__id__":53},"_components":[{"__type__":"cc.Sprite","node":{"__id__":64},"_materials":[{"__uuid__":"ecpdLyjvZBwrvm+cedCcQy"}],"_spriteFrame":{"__uuid__":"6fL8yaMWBIdq/C7vr/K4AZ"}},{"__type__":"cc.Button","node":{"__id__":64},"clickEvents":[{"__type__":"cc.ClickEvent","target":{"__id__":50}}],"_N$transition":2,"transition":2,"_N$normalSprite":{"__uuid__":"6fL8yaMWBIdq/C7vr/K4AZ"},"_N$pressedSprite":{"__uuid__":"f8f4+Y5alJFrscqV2n9jNz"},"pressedSprite":{"__uuid__":"f8f4+Y5alJFrscqV2n9jNz"},"_N$hoverSprite":{"__uuid__":"6fL8yaMWBIdq/C7vr/K4AZ"},"hoverSprite":{"__uuid__":"6fL8yaMWBIdq/C7vr/K4AZ"},"_N$disabledSprite":{"__uuid__":"f8f4+Y5alJFrscqV2n9jNz"},"_N$target":{"__id__":64}}],"_prefab":{"__type__":"cc.PrefabInfo","root":{"__id__":1},"asset":{"__uuid__":"b4srmF86tNvI2ufV08B/aK"},"fileId":"d0RRsvI0xBnqu4TPgZ0wVE"},"_contentSize":{"__type__":"cc.Size","width":60,"height":184},"_trs":{"__type__":"TypedArray","ctor":"Float64Array","array":[177,1,0,0,0,0,1,1,1,1]}},{"__type__":"cc.Node","_name":"btn_chatlist","_parent":{"__id__":53},"_components":[{"__type__":"cc.Sprite","node":{"__id__":65},"_materials":[{"__uuid__":"ecpdLyjvZBwrvm+cedCcQy"}],"_spriteFrame":{"__uuid__":"9bApaokLNFWLKqjD38/5Oy"}},{"__type__":"cc.Button","node":{"__id__":65},"clickEvents":[{"__type__":"cc.ClickEvent","target":{"__id__":65}}],"_N$transition":2,"transition":2,"_N$normalSprite":{"__uuid__":"9bApaokLNFWLKqjD38/5Oy"},"_N$pressedSprite":{"__uuid__":"00T98ynvFPF5oImrPQiIGZ"},"pressedSprite":{"__uuid__":"00T98ynvFPF5oImrPQiIGZ"},"_N$hoverSprite":{"__uuid__":"9bApaokLNFWLKqjD38/5Oy"},"hoverSprite":{"__uuid__":"9bApaokLNFWLKqjD38/5Oy"},"_N$disabledSprite":{"__uuid__":"00T98ynvFPF5oImrPQiIGZ"},"_N$target":{"__id__":65}}],"_prefab":{"__type__":"cc.PrefabInfo","root":{"__id__":1},"asset":{"__uuid__":"b4srmF86tNvI2ufV08B/aK"},"fileId":"b9UBscjGlMSK+E0buhuw3N"},"_contentSize":{"__type__":"cc.Size","width":60,"height":184},"_trs":{"__type__":"TypedArray","ctor":"Float64Array","array":[177,-179,0,0,0,0,1,1,1,1]}},{"__type__":"cc.Node","_name":"chatuser_item","_parent":{"__id__":50},"_children":[{"__id__":67},{"__id__":69},{"__id__":71},{"__id__":72},{"__id__":73},{"__id__":74}],"_active":false,"_components":[{"__type__":"cc.Sprite","node":{"__id__":66},"_materials":[{"__uuid__":"ecpdLyjvZBwrvm+cedCcQy"}]}],"_prefab":{"__type__":"cc.PrefabInfo","root":{"__id__":1},"asset":{"__uuid__":"b4srmF86tNvI2ufV08B/aK"},"fileId":"baHmJA4glPa4/fjpysD7hC"},"_contentSize":{"__type__":"cc.Size","width":320,"height":110},"_trs":{"__type__":"TypedArray","ctor":"Float64Array","array":[0,0,0,0,0,0,1,1,1,1]}},{"__type__":"cc.Node","_name":"headframe","_parent":{"__id__":66},"_children":[{"__id__":68}],"_components":[{"__type__":"cc.Sprite","node":{"__id__":67},"_materials":[{"__uuid__":"ecpdLyjvZBwrvm+cedCcQy"}],"_spriteFrame":{"__uuid__":"05R84DFnFBc6gBhGr/ZhCf"},"_sizeMode":0}],"_prefab":{"__type__":"cc.PrefabInfo","root":{"__id__":1},"asset":{"__uuid__":"b4srmF86tNvI2ufV08B/aK"},"fileId":"9c1vPVPflADq2otc4SFk3S"},"_contentSize":{"__type__":"cc.Size","width":80,"height":80},"_trs":{"__type__":"TypedArray","ctor":"Float64Array","array":[-107,0,0,0,0,0,1,1,1,1]}},{"__type__":"cc.Node","_name":"img_lrstouxiang2","_parent":{"__id__":67},"_components":[{"__type__":"cc.Sprite","node":{"__id__":68},"_materials":[{"__uuid__":"ecpdLyjvZBwrvm+cedCcQy"}],"_spriteFrame":{"__uuid__":"21E5+TlTFPG60blrmNxK6h"},"_sizeMode":0}],"_prefab":{"__type__":"cc.PrefabInfo","root":{"__id__":1},"asset":{"__uuid__":"b4srmF86tNvI2ufV08B/aK"},"fileId":"68pBKAsOlJJYsdTsLPlQpV"},"_contentSize":{"__type__":"cc.Size","width":68,"height":68},"_trs":{"__type__":"TypedArray","ctor":"Float64Array","array":[0,0,0,0,0,0,1,1,1,1]}},{"__type__":"cc.Node","_name":"headnode","_parent":{"__id__":66},"_children":[{"__id__":70}],"_components":[{"__type__":"cc.Mask","node":{"__id__":69},"_materials":[{"__uuid__":"ecpdLyjvZBwrvm+cedCcQy"}],"_type":1,"_N$alphaThreshold":0}],"_prefab":{"__type__":"cc.PrefabInfo","root":{"__id__":1},"asset":{"__uuid__":"b4srmF86tNvI2ufV08B/aK"},"fileId":"c0IB0O/6VDuqljNuOTiHnP"},"_contentSize":{"__type__":"cc.Size","width":65,"height":65},"_trs":{"__type__":"TypedArray","ctor":"Float64Array","array":[-107,0,0,0,0,0,1,1,1,1]}},{"__type__":"cc.Node","_name":"head","_parent":{"__id__":69},"_components":[{"__type__":"cc.Sprite","node":{"__id__":70},"_materials":[{"__uuid__":"ecpdLyjvZBwrvm+cedCcQy"}],"_sizeMode":0}],"_prefab":{"__type__":"cc.PrefabInfo","root":{"__id__":1},"asset":{"__uuid__":"b4srmF86tNvI2ufV08B/aK"},"fileId":"f5mU9+XPVNJ4Sg+XAzUcAb"},"_contentSize":{"__type__":"cc.Size","width":65,"height":65},"_trs":{"__type__":"TypedArray","ctor":"Float64Array","array":[0,0,0,0,0,0,1,1,1,1]}},{"__type__":"cc.Node","_name":"txt","_parent":{"__id__":66},"_active":false,"_components":[{"__type__":"cc.Label","node":{"__id__":71},"_materials":[{"__uuid__":"ecpdLyjvZBwrvm+cedCcQy"}],"_useOriginalSize":false,"_string":"玩家金币玩家金币玩家金币大概多少申达股份单方事故","_N$string":"玩家金币玩家金币玩家金币大概多少申达股份单方事故","_fontSize":22,"_lineHeight":24,"_N$file":{"__uuid__":"077ozJbA1P0oN2tphywD7U"},"_isSystemFontUsed":false,"_N$verticalAlign":1,"_N$overflow":2,"_N$cacheMode":2}],"_prefab":{"__type__":"cc.PrefabInfo","root":{"__id__":1},"asset":{"__uuid__":"b4srmF86tNvI2ufV08B/aK"},"fileId":"38l/R3cZ9LMaGhhSBI2bqg"},"_color":{"__type__":"cc.Color","r":34,"g":16,"b":7},"_contentSize":{"__type__":"cc.Size","width":198,"height":48},"_anchorPoint":{"__type__":"cc.Vec2","y":0.5},"_trs":{"__type__":"TypedArray","ctor":"Float64Array","array":[-54,-8,0,0,0,0,1,1,1,1]}},{"__type__":"cc.Node","_name":"line_lrs","_parent":{"__id__":66},"_components":[{"__type__":"cc.Sprite","node":{"__id__":72},"_materials":[{"__uuid__":"ecpdLyjvZBwrvm+cedCcQy"}],"_spriteFrame":{"__uuid__":"1eTRtXoK1Fq6sgvNDpo3X7"}}],"_prefab":{"__type__":"cc.PrefabInfo","root":{"__id__":1},"asset":{"__uuid__":"b4srmF86tNvI2ufV08B/aK"},"fileId":"dcpfy4DeBBIpi37UIupKnQ"},"_contentSize":{"__type__":"cc.Size","width":304,"height":19},"_trs":{"__type__":"TypedArray","ctor":"Float64Array","array":[0,-44,0,0,0,0,1,1,1,1]}},{"__type__":"cc.Node","_name":"bq","_parent":{"__id__":66},"_active":false,"_components":[{"__type__":"cc.Sprite","node":{"__id__":73},"_materials":[{"__uuid__":"ecpdLyjvZBwrvm+cedCcQy"}],"_spriteFrame":{"__uuid__":"6djk7J//lIl6xqzTg+XAH4"}}],"_prefab":{"__type__":"cc.PrefabInfo","root":{"__id__":1},"asset":{"__uuid__":"b4srmF86tNvI2ufV08B/aK"},"fileId":"57Xesy+N9PuaSfU//vAG0q"},"_contentSize":{"__type__":"cc.Size","width":50,"height":50},"_trs":{"__type__":"TypedArray","ctor":"Float64Array","array":[40,-6,0,0,0,0,1,1,1,1]}},{"__type__":"cc.Node","_name":"name","_parent":{"__id__":66},"_components":[{"__type__":"cc.Label","node":{"__id__":74},"_materials":[{"__uuid__":"ecpdLyjvZBwrvm+cedCcQy"}],"_useOriginalSize":false,"_fontSize":20,"_lineHeight":20,"_N$file":{"__uuid__":"077ozJbA1P0oN2tphywD7U"},"_isSystemFontUsed":false,"_N$horizontalAlign":1,"_N$verticalAlign":1,"_N$overflow":2},{"__type__":"cc.LabelOutline","node":{"__id__":74},"_color":{"__type__":"cc.Color","r":101,"g":91,"b":52},"_width":2}],"_prefab":{"__type__":"cc.PrefabInfo","root":{"__id__":1},"asset":{"__uuid__":"b4srmF86tNvI2ufV08B/aK"},"fileId":"23RQi6cWVG0JKEBT0vJxdm"},"_color":{"__type__":"cc.Color","r":248,"g":230,"b":184},"_contentSize":{"__type__":"cc.Size","width":104,"height":29.2},"_trs":{"__type__":"TypedArray","ctor":"Float64Array","array":[-106,-33,0,0,0,0,1,1,1,1]}},{"__type__":"cc.Node","_name":"chattxt_item","_parent":{"__id__":50},"_children":[{"__id__":76},{"__id__":77},{"__id__":78}],"_active":false,"_components":[{"__type__":"cc.Sprite","node":{"__id__":75},"_materials":[{"__uuid__":"ecpdLyjvZBwrvm+cedCcQy"}]},{"__type__":"cc.Button","node":{"__id__":75},"_N$target":{"__id__":75}}],"_prefab":{"__type__":"cc.PrefabInfo","root":{"__id__":1},"asset":{"__uuid__":"b4srmF86tNvI2ufV08B/aK"},"fileId":"b95nD/GLdH95iKCsSX2EmC"},"_contentSize":{"__type__":"cc.Size","width":320,"height":70},"_trs":{"__type__":"TypedArray","ctor":"Float64Array","array":[0,0,0,0,0,0,1,1,1,1]}},{"__type__":"cc.Node","_name":"txt","_parent":{"__id__":75},"_components":[{"__type__":"cc.Label","node":{"__id__":76},"_materials":[{"__uuid__":"ecpdLyjvZBwrvm+cedCcQy"}],"_useOriginalSize":false,"_string":"快捷语1","_N$string":"快捷语1","_fontSize":22,"_lineHeight":24,"_N$file":{"__uuid__":"077ozJbA1P0oN2tphywD7U"},"_isSystemFontUsed":false,"_N$horizontalAlign":1,"_N$verticalAlign":1,"_N$cacheMode":2}],"_prefab":{"__type__":"cc.PrefabInfo","root":{"__id__":1},"asset":{"__uuid__":"b4srmF86tNvI2ufV08B/aK"},"fileId":"3fRrom9NVLco9Ed5R7MpUr"},"_color":{"__type__":"cc.Color","r":34,"g":16,"b":7},"_contentSize":{"__type__":"cc.Size","width":77,"height":24},"_anchorPoint":{"__type__":"cc.Vec2","y":0.5},"_trs":{"__type__":"TypedArray","ctor":"Float64Array","array":[-140,0,0,0,0,0,1,1,1,1]}},{"__type__":"cc.Node","_name":"line","_parent":{"__id__":75},"_components":[{"__type__":"cc.Sprite","node":{"__id__":77},"_materials":[{"__uuid__":"ecpdLyjvZBwrvm+cedCcQy"}],"_spriteFrame":{"__uuid__":"1eTRtXoK1Fq6sgvNDpo3X7"},"_sizeMode":0}],"_prefab":{"__type__":"cc.PrefabInfo","root":{"__id__":1},"asset":{"__uuid__":"b4srmF86tNvI2ufV08B/aK"},"fileId":"222Fd46h1OQ5f89SXGwMls"},"_contentSize":{"__type__":"cc.Size","width":304,"height":20},"_trs":{"__type__":"TypedArray","ctor":"Float64Array","array":[-2,-26,0,0,0,0,1,1,1,1]}},{"__type__":"cc.Node","_name":"select","_parent":{"__id__":75},"_active":false,"_components":[{"__type__":"cc.Sprite","node":{"__id__":78},"_materials":[{"__uuid__":"ecpdLyjvZBwrvm+cedCcQy"}],"_spriteFrame":{"__uuid__":"c82H0W2JBMv4mgFjMlmmPa"}}],"_prefab":{"__type__":"cc.PrefabInfo","root":{"__id__":1},"asset":{"__uuid__":"b4srmF86tNvI2ufV08B/aK"},"fileId":"9d6nkRhtJFUYPpcRVLhL5C"},"_contentSize":{"__type__":"cc.Size","width":314,"height":60},"_trs":{"__type__":"TypedArray","ctor":"Float64Array","array":[0,0,0,0,0,0,1,1,1,1]}},{"__type__":"cc.Node","_name":"chatbq_item","_parent":{"__id__":50},"_children":[{"__id__":80}],"_active":false,"_components":[{"__type__":"cc.Sprite","node":{"__id__":79},"_materials":[{"__uuid__":"ecpdLyjvZBwrvm+cedCcQy"}]},{"__type__":"cc.Button","node":{"__id__":79},"_N$target":{"__id__":79}}],"_prefab":{"__type__":"cc.PrefabInfo","root":{"__id__":1},"asset":{"__uuid__":"b4srmF86tNvI2ufV08B/aK"},"fileId":"cd7ac/YCNGh7BN4FhVGSe0"},"_contentSize":{"__type__":"cc.Size","width":60,"height":70},"_trs":{"__type__":"TypedArray","ctor":"Float64Array","array":[0,0,0,0,0,0,1,1,1,1]}},{"__type__":"cc.Node","_name":"bq","_parent":{"__id__":79},"_components":[{"__type__":"cc.Sprite","node":{"__id__":80},"_materials":[{"__uuid__":"ecpdLyjvZBwrvm+cedCcQy"}],"_spriteFrame":{"__uuid__":"6djk7J//lIl6xqzTg+XAH4"}}],"_prefab":{"__type__":"cc.PrefabInfo","root":{"__id__":1},"asset":{"__uuid__":"b4srmF86tNvI2ufV08B/aK"},"fileId":"0f9G55djlAlqWWpBHaCOZV"},"_contentSize":{"__type__":"cc.Size","width":50,"height":50},"_trs":{"__type__":"TypedArray","ctor":"Float64Array","array":[0,0,0,0,0,0,1,1,1,1]}},{"__type__":"d3cdapoyoZMP4JOiF0f96KW","node":{"__id__":50},"cancel":{"__id__":2},"spr":{"__id__":52},"btn_click":{"__id__":51},"btn_txt":{"__id__":63},"btn_bq":{"__id__":64},"btn_list":{"__id__":65},"user_panel":{"__id__":53},"ScrollView_txt":{"__id__":54},"ScrollView_bq":{"__id__":57},"ScrollView_list":{"__id__":60},"user_item":{"__id__":66},"bq_item":{"__id__":79},"txt_item":{"__id__":75}},{"__type__":"cc.Node","_name":"node_top","_parent":{"__id__":1},"_children":[{"__id__":83},{"__id__":84},{"__id__":86},{"__id__":95},{"__id__":97}],"_components":[{"__type__":"cc.Widget","node":{"__id__":82},"_alignFlags":41},{"__id__":108}],"_prefab":{"__type__":"cc.PrefabInfo","root":{"__id__":1},"asset":{"__uuid__":"b4srmF86tNvI2ufV08B/aK"},"fileId":"e3u+Y1jxFOyoxqqf+vHB3/"},"_contentSize":{"__type__":"cc.Size","width":1280,"height":80},"_trs":{"__type__":"TypedArray","ctor":"Float64Array","array":[0,320,0,0,0,0,1,1,1,1]}},{"__type__":"cc.Node","_name":"btn_cancel","_parent":{"__id__":82},"_active":false,"_components":[{"__type__":"cc.Widget","node":{"__id__":83},"_target":{"__id__":1},"_alignFlags":45}],"_prefab":{"__type__":"cc.PrefabInfo","root":{"__id__":1},"asset":{"__uuid__":"b4srmF86tNvI2ufV08B/aK"},"fileId":"e1t3OBfm5HHpiO8+LH4jDY"},"_contentSize":{"__type__":"cc.Size","width":1280,"height":720},"_trs":{"__type__":"TypedArray","ctor":"Float64Array","array":[0,-320,0,0,0,0,1,1,1,1]}},{"__type__":"cc.Node","_name":"img_tg03","_parent":{"__id__":82},"_children":[{"__id__":85}],"_active":false,"_components":[{"__type__":"cc.Sprite","node":{"__id__":84},"_materials":[{"__uuid__":"ecpdLyjvZBwrvm+cedCcQy"}],"_spriteFrame":{"__uuid__":"37r0i4IR1Hf5GIZVetbIWy"},"_type":1,"_sizeMode":0}],"_prefab":{"__type__":"cc.PrefabInfo","root":{"__id__":1},"asset":{"__uuid__":"b4srmF86tNvI2ufV08B/aK"},"fileId":"4fWQhpIX9OoZhUxcmy5OOW"},"_color":{"__type__":"cc.Color"},"_contentSize":{"__type__":"cc.Size","width":108,"height":38},"_trs":{"__type__":"TypedArray","ctor":"Float64Array","array":[-460,0,0,0,0,0,1,1,1,1]}},{"__type__":"cc.Node","_name":"label","_parent":{"__id__":84},"_components":[{"__type__":"cc.Label","node":{"__id__":85},"_materials":[{"__uuid__":"ecpdLyjvZBwrvm+cedCcQy"}],"_useOriginalSize":false,"_string":"底注:","_N$string":"底注:","_fontSize":22,"_lineHeight":24,"_N$file":{"__uuid__":"077ozJbA1P0oN2tphywD7U"},"_isSystemFontUsed":false,"_N$horizontalAlign":1,"_N$verticalAlign":1}],"_prefab":{"__type__":"cc.PrefabInfo","root":{"__id__":1},"asset":{"__uuid__":"b4srmF86tNvI2ufV08B/aK"},"fileId":"25hL1+oChLFZGonsgF8+W1"},"_contentSize":{"__type__":"cc.Size","width":50.11,"height":30.24},"_anchorPoint":{"__type__":"cc.Vec2","y":0.5},"_trs":{"__type__":"TypedArray","ctor":"Float64Array","array":[-42,0,0,0,0,0,1,1,1,1]}},{"__type__":"cc.Node","_name":"New Node","_parent":{"__id__":82},"_children":[{"__id__":87},{"__id__":91}],"_components":[{"__type__":"cc.Layout","node":{"__id__":86},"_layoutSize":{"__type__":"cc.Size","width":-30,"height":40},"_resize":1,"_N$layoutType":1,"_N$spacingX":30}],"_prefab":{"__type__":"cc.PrefabInfo","root":{"__id__":1},"asset":{"__uuid__":"b4srmF86tNvI2ufV08B/aK"},"fileId":"b7c0qvDdlNDZHegC6FjCoC"},"_contentSize":{"__type__":"cc.Size","width":-30,"height":40},"_anchorPoint":{"__type__":"cc.Vec2","y":0.5},"_trs":{"__type__":"TypedArray","ctor":"Float64Array","array":[-375,0,0,0,0,0,1,1,1,1]}},{"__type__":"cc.Node","_name":"img_tg03","_parent":{"__id__":86},"_children":[{"__id__":88},{"__id__":89}],"_active":false,"_components":[{"__type__":"cc.Sprite","node":{"__id__":87},"_materials":[{"__uuid__":"ecpdLyjvZBwrvm+cedCcQy"}],"_spriteFrame":{"__uuid__":"37r0i4IR1Hf5GIZVetbIWy"},"_type":1,"_sizeMode":0},{"__type__":"cc.Layout","node":{"__id__":87},"_layoutSize":{"__type__":"cc.Size","width":125,"height":38.24},"_resize":1,"_N$paddingLeft":10,"_N$paddingRight":10,"_N$paddingTop":4,"_N$paddingBottom":4}],"_prefab":{"__type__":"cc.PrefabInfo","root":{"__id__":1},"asset":{"__uuid__":"b4srmF86tNvI2ufV08B/aK"},"fileId":"bbNYacAYtK5abHaZEOVfrw"},"_color":{"__type__":"cc.Color"},"_contentSize":{"__type__":"cc.Size","width":125,"height":38.24},"_anchorPoint":{"__type__":"cc.Vec2","x":1.76,"y":0.5},"_trs":{"__type__":"TypedArray","ctor":"Float64Array","array":[220,0,0,0,0,0,1,1,1,1]}},{"__type__":"cc.Node","_name":"label","_parent":{"__id__":87},"_components":[{"__type__":"cc.Label","node":{"__id__":88},"_materials":[{"__uuid__":"ecpdLyjvZBwrvm+cedCcQy"}],"_useOriginalSize":false,"_string":"牌局编号:","_N$string":"牌局编号:","_fontSize":22,"_lineHeight":24,"_N$file":{"__uuid__":"077ozJbA1P0oN2tphywD7U"},"_isSystemFontUsed":false,"_N$horizontalAlign":1,"_N$verticalAlign":1}],"_prefab":{"__type__":"cc.PrefabInfo","root":{"__id__":1},"asset":{"__uuid__":"b4srmF86tNvI2ufV08B/aK"},"fileId":"d1LWc6GmtFI77gjCsDzYoK"},"_contentSize":{"__type__":"cc.Size","width":94.11,"height":30.24},"_anchorPoint":{"__type__":"cc.Vec2","y":0.5},"_trs":{"__type__":"TypedArray","ctor":"Float64Array","array":[-210,0,0,0,0,0,1,1,1,1]}},{"__type__":"cc.Node","_name":"table_num","_parent":{"__id__":87},"_components":[{"__id__":90}],"_prefab":{"__type__":"cc.PrefabInfo","root":{"__id__":1},"asset":{"__uuid__":"b4srmF86tNvI2ufV08B/aK"},"fileId":"d7lxU24I5EhaUszXlknYhL"},"_contentSize":{"__type__":"cc.Size","height":30.24},"_anchorPoint":{"__type__":"cc.Vec2","y":0.5},"_trs":{"__type__":"TypedArray","ctor":"Float64Array","array":[-105,0,0,0,0,0,1,1,1,1]}},{"__type__":"cc.Label","node":{"__id__":89},"_materials":[{"__uuid__":"ecpdLyjvZBwrvm+cedCcQy"}],"_useOriginalSize":false,"_fontSize":22,"_lineHeight":24,"_N$file":{"__uuid__":"077ozJbA1P0oN2tphywD7U"},"_isSystemFontUsed":false,"_N$horizontalAlign":1,"_N$verticalAlign":1},{"__type__":"cc.Node","_name":"img_tg04","_parent":{"__id__":86},"_children":[{"__id__":92},{"__id__":93}],"_active":false,"_components":[{"__type__":"cc.Sprite","node":{"__id__":91},"_materials":[{"__uuid__":"ecpdLyjvZBwrvm+cedCcQy"}],"_spriteFrame":{"__uuid__":"37r0i4IR1Hf5GIZVetbIWy"},"_type":1,"_sizeMode":0},{"__type__":"cc.Layout","node":{"__id__":91},"_layoutSize":{"__type__":"cc.Size","width":93,"height":38.24},"_resize":1,"_N$paddingLeft":10,"_N$paddingRight":10,"_N$paddingTop":4,"_N$paddingBottom":4}],"_prefab":{"__type__":"cc.PrefabInfo","root":{"__id__":1},"asset":{"__uuid__":"b4srmF86tNvI2ufV08B/aK"},"fileId":"aef5IE4UlGVKoW0U5rrHHp"},"_color":{"__type__":"cc.Color"},"_contentSize":{"__type__":"cc.Size","width":93,"height":38.24},"_anchorPoint":{"__type__":"cc.Vec2","x":2.37,"y":0.5},"_trs":{"__type__":"TypedArray","ctor":"Float64Array","array":[220.41,0,0,0,0,0,1,1,1,1]}},{"__type__":"cc.Node","_name":"label","_parent":{"__id__":91},"_components":[{"__type__":"cc.Label","node":{"__id__":92},"_materials":[{"__uuid__":"ecpdLyjvZBwrvm+cedCcQy"}],"_useOriginalSize":false,"_string":"房间号:","_N$string":"房间号:","_fontSize":22,"_lineHeight":24,"_N$file":{"__uuid__":"077ozJbA1P0oN2tphywD7U"},"_isSystemFontUsed":false,"_N$horizontalAlign":1,"_N$verticalAlign":1}],"_prefab":{"__type__":"cc.PrefabInfo","root":{"__id__":1},"asset":{"__uuid__":"b4srmF86tNvI2ufV08B/aK"},"fileId":"28i8uPZNBJ0bgasMy/3Dgw"},"_contentSize":{"__type__":"cc.Size","width":72.11,"height":30.24},"_anchorPoint":{"__type__":"cc.Vec2","y":0.5},"_trs":{"__type__":"TypedArray","ctor":"Float64Array","array":[-210,0,0,0,0,0,1,1,1,1]}},{"__type__":"cc.Node","_name":"room_id","_parent":{"__id__":91},"_components":[{"__id__":94}],"_prefab":{"__type__":"cc.PrefabInfo","root":{"__id__":1},"asset":{"__uuid__":"b4srmF86tNvI2ufV08B/aK"},"fileId":"94PnF80LZIpaA+7v+4amIx"},"_contentSize":{"__type__":"cc.Size","height":30.24},"_anchorPoint":{"__type__":"cc.Vec2","y":0.5},"_trs":{"__type__":"TypedArray","ctor":"Float64Array","array":[-137,0,0,0,0,0,1,1,1,1]}},{"__type__":"cc.Label","node":{"__id__":93},"_materials":[{"__uuid__":"ecpdLyjvZBwrvm+cedCcQy"}],"_useOriginalSize":false,"_fontSize":22,"_lineHeight":24,"_N$file":{"__uuid__":"077ozJbA1P0oN2tphywD7U"},"_isSystemFontUsed":false,"_N$horizontalAlign":1,"_N$verticalAlign":1},{"__type__":"cc.Node","_name":"pot_num","_parent":{"__id__":82},"_components":[{"__id__":96}],"_prefab":{"__type__":"cc.PrefabInfo","root":{"__id__":1},"asset":{"__uuid__":"b4srmF86tNvI2ufV08B/aK"},"fileId":"34Hy+YVdJObZD/sPWHIc0b"},"_contentSize":{"__type__":"cc.Size","height":30.24},"_trs":{"__type__":"TypedArray","ctor":"Float64Array","array":[-434,0,0,0,0,0,1,1,1,1]}},{"__type__":"cc.Label","node":{"__id__":95},"_materials":[{"__uuid__":"ecpdLyjvZBwrvm+cedCcQy"}],"_useOriginalSize":false,"_fontSize":22,"_lineHeight":24,"_N$file":{"__uuid__":"077ozJbA1P0oN2tphywD7U"},"_isSystemFontUsed":false,"_N$horizontalAlign":1,"_N$verticalAlign":1},{"__type__":"cc.Node","_name":"MulMenuPanel","_parent":{"__id__":82},"_children":[{"__id__":98},{"__id__":99}],"_components":[{"__type__":"cc.Widget","node":{"__id__":97},"_alignFlags":33,"_right":55,"_top":40}],"_prefab":{"__type__":"cc.PrefabInfo","root":{"__id__":1},"asset":{"__uuid__":"b4srmF86tNvI2ufV08B/aK"},"fileId":"1fJgHoellMdKS2DGWxNZCN"},"_trs":{"__type__":"TypedArray","ctor":"Float64Array","array":[585,0,0,0,0,0,1,1,1,1]}},{"__type__":"cc.Node","_name":"btn_menu","_parent":{"__id__":97},"_components":[{"__type__":"cc.Sprite","node":{"__id__":98},"_materials":[{"__uuid__":"ecpdLyjvZBwrvm+cedCcQy"}],"_spriteFrame":{"__uuid__":"6eLry29t1AK7Ctas+dxjN8"}}],"_prefab":{"__type__":"cc.PrefabInfo","root":{"__id__":1},"asset":{"__uuid__":"b4srmF86tNvI2ufV08B/aK"},"fileId":"f7wYb+Bg5IFoJhYL7ImSN7"},"_contentSize":{"__type__":"cc.Size","width":56,"height":77},"_trs":{"__type__":"TypedArray","ctor":"Float64Array","array":[0,0,0,0,0,0,1,1,1,1]}},{"__type__":"cc.Node","_name":"panel","_parent":{"__id__":97},"_children":[{"__id__":100},{"__id__":102},{"__id__":104},{"__id__":106},{"__id__":107}],"_active":false,"_components":[{"__type__":"cc.Sprite","node":{"__id__":99},"_materials":[{"__uuid__":"ecpdLyjvZBwrvm+cedCcQy"}],"_spriteFrame":{"__uuid__":"1233VhZSNPd71rpKCQ8L0z"},"_sizeMode":2},{"__type__":"cc.BlockInputEvents","node":{"__id__":99}}],"_prefab":{"__type__":"cc.PrefabInfo","root":{"__id__":1},"asset":{"__uuid__":"b4srmF86tNvI2ufV08B/aK"},"fileId":"0eFPMU/LtA/7VvIP3J9zQC"},"_contentSize":{"__type__":"cc.Size","width":168,"height":352},"_trs":{"__type__":"TypedArray","ctor":"Float64Array","array":[-46,-216,0,0,0,0,1,1,1,1]}},{"__type__":"cc.Node","_name":"btn_set","_parent":{"__id__":99},"_children":[{"__id__":101}],"_prefab":{"__type__":"cc.PrefabInfo","root":{"__id__":1},"asset":{"__uuid__":"b4srmF86tNvI2ufV08B/aK"},"fileId":"91Iz45MUtJ25QjtJ7Emk6G"},"_contentSize":{"__type__":"cc.Size","width":120,"height":60},"_trs":{"__type__":"TypedArray","ctor":"Float64Array","array":[10,112,0,0,0,0,1,1,1,1]}},{"__type__":"cc.Node","_name":"font_shezhi","_parent":{"__id__":100},"_components":[{"__type__":"cc.Sprite","node":{"__id__":101},"_materials":[{"__uuid__":"ecpdLyjvZBwrvm+cedCcQy"}],"_spriteFrame":{"__uuid__":"daiiWCS2JBw5oahtg44YfG"}}],"_prefab":{"__type__":"cc.PrefabInfo","root":{"__id__":1},"asset":{"__uuid__":"b4srmF86tNvI2ufV08B/aK"},"fileId":"f156U+mXdD04D6oi4I/SWV"},"_contentSize":{"__type__":"cc.Size","width":118,"height":42},"_trs":{"__type__":"TypedArray","ctor":"Float64Array","array":[0,0,0,0,0,0,1,1,1,1]}},{"__type__":"cc.Node","_name":"btn_rule","_parent":{"__id__":99},"_children":[{"__id__":103}],"_prefab":{"__type__":"cc.PrefabInfo","root":{"__id__":1},"asset":{"__uuid__":"b4srmF86tNvI2ufV08B/aK"},"fileId":"2b2yT1jfZMH5bBzOxLQ82T"},"_contentSize":{"__type__":"cc.Size","width":120,"height":60},"_trs":{"__type__":"TypedArray","ctor":"Float64Array","array":[10,14,0,0,0,0,1,1,1,1]}},{"__type__":"cc.Node","_name":"font_guize","_parent":{"__id__":102},"_components":[{"__type__":"cc.Sprite","node":{"__id__":103},"_materials":[{"__uuid__":"ecpdLyjvZBwrvm+cedCcQy"}],"_spriteFrame":{"__uuid__":"287lPTi5ND9bk1DLt2mIzn"}}],"_prefab":{"__type__":"cc.PrefabInfo","root":{"__id__":1},"asset":{"__uuid__":"b4srmF86tNvI2ufV08B/aK"},"fileId":"3c/PwEqUVMPomxQWmRo1+S"},"_contentSize":{"__type__":"cc.Size","width":120,"height":35},"_trs":{"__type__":"TypedArray","ctor":"Float64Array","array":[0,0,0,0,0,0,1,1,1,1]}},{"__type__":"cc.Node","_name":"btn_back","_parent":{"__id__":99},"_children":[{"__id__":105}],"_prefab":{"__type__":"cc.PrefabInfo","root":{"__id__":1},"asset":{"__uuid__":"b4srmF86tNvI2ufV08B/aK"},"fileId":"7dikDoZfZMaqAvaa1HJpBB"},"_contentSize":{"__type__":"cc.Size","width":120,"height":60},"_trs":{"__type__":"TypedArray","ctor":"Float64Array","array":[10,-85,0,0,0,0,1,1,1,1]}},{"__type__":"cc.Node","_name":"font_back","_parent":{"__id__":104},"_components":[{"__type__":"cc.Sprite","node":{"__id__":105},"_materials":[{"__uuid__":"ecpdLyjvZBwrvm+cedCcQy"}],"_spriteFrame":{"__uuid__":"74tc7OnV1GroT1ddIN8vpM"}}],"_prefab":{"__type__":"cc.PrefabInfo","root":{"__id__":1},"asset":{"__uuid__":"b4srmF86tNvI2ufV08B/aK"},"fileId":"c7CDYdqRtFfZU0R7WSorG7"},"_contentSize":{"__type__":"cc.Size","width":123,"height":39},"_trs":{"__type__":"TypedArray","ctor":"Float64Array","array":[0,0,0,0,0,0,1,1,1,1]}},{"__type__":"cc.Node","_name":"spr_line","_parent":{"__id__":99},"_active":false,"_components":[{"__type__":"cc.Sprite","node":{"__id__":106},"_materials":[{"__uuid__":"ecpdLyjvZBwrvm+cedCcQy"}],"_spriteFrame":{"__uuid__":"78t2VIxaZPWKTAjjw2QDUB"}}],"_prefab":{"__type__":"cc.PrefabInfo","root":{"__id__":1},"asset":{"__uuid__":"b4srmF86tNvI2ufV08B/aK"},"fileId":"6fAdIsM1BBPrCx81bBgDSw"},"_contentSize":{"__type__":"cc.Size","width":127,"height":9},"_trs":{"__type__":"TypedArray","ctor":"Float64Array","array":[0,-38,0,0,0,0,1,1,1,1]}},{"__type__":"cc.Node","_name":"spr_line","_parent":{"__id__":99},"_active":false,"_components":[{"__type__":"cc.Sprite","node":{"__id__":107},"_materials":[{"__uuid__":"ecpdLyjvZBwrvm+cedCcQy"}],"_spriteFrame":{"__uuid__":"78t2VIxaZPWKTAjjw2QDUB"}}],"_prefab":{"__type__":"cc.PrefabInfo","root":{"__id__":1},"asset":{"__uuid__":"b4srmF86tNvI2ufV08B/aK"},"fileId":"4cMnJuTqtN373EFPEIlEOW"},"_contentSize":{"__type__":"cc.Size","width":127,"height":9},"_trs":{"__type__":"TypedArray","ctor":"Float64Array","array":[0,38,0,0,0,0,1,1,1,1]}},{"__type__":"7b94ar4B85OhJGa8kdkAPKd","node":{"__id__":82},"pot_num":{"__id__":96},"table_num":{"__id__":90},"room_id":{"__id__":94},"room_id_node":{"__id__":91},"btn_cancel":{"__id__":83},"btn_menu":{"__id__":98},"menuPanel":{"__id__":99},"btn_back":{"__id__":104},"btn_rule":{"__id__":102},"btn_set":{"__id__":100}},{"__type__":"e35a1Sbu7tKUbp3iulneLCh","node":{"__id__":1},"spr_bg":{"__id__":5},"node_top":{"__id__":82},"node_center":{"__id__":6},"topPanel":{"__id__":108},"centerPanel":{"__id__":48},"chatView":{"__id__":81},"UINode":{"__id__":49}}],{"__type__":"cc.SpriteFrame","content":{"name":"img_xuanzhong_org","texture":"1fd604ce8","rect":[942,3,314,60],"offset":[0,0],"originalSize":[314,60],"rotated":1,"capInsets":[0,0,0,0]}},{"__type__":"cc.SpriteFrame","content":{"name":"btn_sz","texture":"766jRIbGpJOJUfvQNOkzed","rect":[0,0,124,43],"offset":[0,0.5],"originalSize":[124,44],"capInsets":[0,0,0,0]}},{"__type__":"cc.SpriteFrame","content":{"name":"img_nvwu_ff","texture":"194ab3360","rect":[356,774,169,238],"offset":[-0.5,0],"originalSize":[170,238],"capInsets":[0,0,0,0]}},{"__type__":"cc.SpriteFrame","content":{"name":"text_bai_yel","texture":"1994e2620","rect":[521,3,62,23],"offset":[0,0.5],"originalSize":[64,24],"capInsets":[0,0,0,0]}},{"__type__":"cc.SpriteFrame","content":{"name":"default_btn_pressed","texture":"b4P/PCArtIdIH38t6mlw8Y","rect":[0,0,40,40],"offset":[0,0],"originalSize":[40,40],"capInsets":[12,12,12,12]}},{"__type__":"cc.SpriteFrame","content":{"name":"default_btn_normal","texture":"e8Ueib+qJEhL6mXAHdnwbi","rect":[0,0,40,40],"offset":[0,0],"originalSize":[40,40],"capInsets":[12,12,12,12]}},{"__type__":"cc.SpriteFrame","content":{"name":"img_bq_yel","texture":"1994e2620","rect":[625,145,60,184],"offset":[0,0],"originalSize":[60,184],"rotated":1,"capInsets":[0,0,0,0]}}]