[[{"__type__":"cc.Prefab","_name":"Coin","data":{"__id__":1}},{"__type__":"cc.Node","_name":"Coin","_components":[{"__type__":"cc.Sprite","node":{"__id__":1},"_materials":[{"__uuid__":"ecpdLyjvZBwrvm+cedCcQy"}],"_spriteFrame":{"__uuid__":"dfY/RCrzFPAJkQecTE12sW"}}],"_prefab":{"__type__":"cc.PrefabInfo","root":{"__id__":1},"asset":{"__id__":0},"fileId":"54K1wUlk9H8rBQxnwCqvmm"},"_contentSize":{"__type__":"cc.Size","width":52,"height":48},"_trs":{"__type__":"TypedArray","ctor":"Float64Array","array":[0,0,0,0,0,0,1,1,1,1]}}],{"__type__":"cc.SpriteFrame","content":{"name":"img_hdwupin","texture":"1dbe092d9","rect":[893,700,52,48],"offset":[0,0],"originalSize":[52,48],"rotated":1,"capInsets":[0,0,0,0]}}]